{".class":"MypyFile","_fullname":"nextcord.types.activity","future_import_flags":["annotations"],"is_partial_stub_package":false,"is_stub":false,"names":{".class":"SymbolTable","Activity":{".class":"SymbolTableNode","kind":"Gdef","node":{".class":"TypeInfo","_promote":[],"abstract_attributes":[],"alt_promote":null,"bases":["typing._TypedDict"],"dataclass_transform_spec":null,"declared_metaclass":null,"defn":{".class":"ClassDef","fullname":"nextcord.types.activity.Activity","name":"Activity","type_vars":[]},"deletable_attributes":[],"flags":[],"fullname":"nextcord.types.activity.Activity","has_param_spec_type":false,"metaclass_type":null,"metadata":{},"module_name":"nextcord.types.activity","mro":["nextcord.types.activity.Activity","typing._TypedDict","typing.Mapping","typing.Collection","typing.Iterable","typing.Container","builtins.object"],"names":{".class":"SymbolTable"},"self_type":null,"slots":null,"tuple_type":null,"type_vars":[],"typeddict_type":{".class":"TypedDictType","fallback":"typing._TypedDict","items":[["name","builtins.str"],["type",{".class":"TypeAliasType","args":[],"type_ref":"nextcord.types.activity.ActivityType"}],["url",{".class":"UnionType","items":["builtins.str",{".class":"NoneType"}]}],["created_at","builtins.int"],["state",{".class":"UnionType","items":["builtins.str",{".class":"NoneType"}]}],["details",{".class":"UnionType","items":["builtins.str",{".class":"NoneType"}]}],["timestamps",{".class":"TypeAliasType","args":[],"type_ref":"nextcord.types.activity.ActivityTimestamps"}],["assets",{".class":"TypeAliasType","args":[],"type_ref":"nextcord.types.activity.ActivityAssets"}],["party",{".class":"TypeAliasType","args":[],"type_ref":"nextcord.types.activity.ActivityParty"}],["application_id",{".class":"TypeAliasType","args":[],"type_ref":"nextcord.types.snowflake.Snowflake"}],["flags","builtins.int"],["emoji",{".class":"UnionType","items":[{".class":"TypeAliasType","args":[],"type_ref":"nextcord.types.activity.ActivityEmoji"},{".class":"NoneType"}]}],["secrets",{".class":"TypeAliasType","args":[],"type_ref":"nextcord.types.activity.ActivitySecrets"}],["session_id",{".class":"UnionType","items":["builtins.str",{".class":"NoneType"}]}],["instance","builtins.bool"],["buttons",{".class":"Instance","args":[{".class":"TypeAliasType","args":[],"type_ref":"nextcord.types.activity.ActivityButton"}],"type_ref":"builtins.list"}]],"required_keys":["created_at","name","type"]}}},"ActivityAssets":{".class":"SymbolTableNode","kind":"Gdef","node":{".class":"TypeInfo","_promote":[],"abstract_attributes":[],"alt_promote":null,"bases":["typing._TypedDict"],"dataclass_transform_spec":null,"declared_metaclass":null,"defn":{".class":"ClassDef","fullname":"nextcord.types.activity.ActivityAssets","name":"ActivityAssets","type_vars":[]},"deletable_attributes":[],"flags":[],"fullname":"nextcord.types.activity.ActivityAssets","has_param_spec_type":false,"metaclass_type":null,"metadata":{},"module_name":"nextcord.types.activity","mro":["nextcord.types.activity.ActivityAssets","typing._TypedDict","typing.Mapping","typing.Collection","typing.Iterable","typing.Container","builtins.object"],"names":{".class":"SymbolTable"},"self_type":null,"slots":null,"tuple_type":null,"type_vars":[],"typeddict_type":{".class":"TypedDictType","fallback":"typing._TypedDict","items":[["large_image","builtins.str"],["large_text","builtins.str"],["small_image","builtins.str"],["small_text","builtins.str"]],"required_keys":[]}}},"ActivityButton":{".class":"SymbolTableNode","kind":"Gdef","node":{".class":"TypeInfo","_promote":[],"abstract_attributes":[],"alt_promote":null,"bases":["typing._TypedDict"],"dataclass_transform_spec":null,"declared_metaclass":null,"defn":{".class":"ClassDef","fullname":"nextcord.types.activity.ActivityButton","name":"ActivityButton","type_vars":[]},"deletable_attributes":[],"flags":[],"fullname":"nextcord.types.activity.ActivityButton","has_param_spec_type":false,"metaclass_type":null,"metadata":{},"module_name":"nextcord.types.activity","mro":["nextcord.types.activity.ActivityButton","typing._TypedDict","typing.Mapping","typing.Collection","typing.Iterable","typing.Container","builtins.object"],"names":{".class":"SymbolTable"},"self_type":null,"slots":null,"tuple_type":null,"type_vars":[],"typeddict_type":{".class":"TypedDictType","fallback":"typing._TypedDict","items":[["label","builtins.str"],["url","builtins.str"]],"required_keys":["label","url"]}}},"ActivityEmoji":{".class":"SymbolTableNode","kind":"Gdef","node":{".class":"TypeInfo","_promote":[],"abstract_attributes":[],"alt_promote":null,"bases":["typing._TypedDict"],"dataclass_transform_spec":null,"declared_metaclass":null,"defn":{".class":"ClassDef","fullname":"nextcord.types.activity.ActivityEmoji","name":"ActivityEmoji","type_vars":[]},"deletable_attributes":[],"flags":[],"fullname":"nextcord.types.activity.ActivityEmoji","has_param_spec_type":false,"metaclass_type":null,"metadata":{},"module_name":"nextcord.types.activity","mro":["nextcord.types.activity.ActivityEmoji","typing._TypedDict","typing.Mapping","typing.Collection","typing.Iterable","typing.Container","builtins.object"],"names":{".class":"SymbolTable"},"self_type":null,"slots":null,"tuple_type":null,"type_vars":[],"typeddict_type":{".class":"TypedDictType","fallback":"typing._TypedDict","items":[["id",{".class":"TypeAliasType","args":[],"type_ref":"nextcord.types.snowflake.Snowflake"}],["animated","builtins.bool"],["name","builtins.str"]],"required_keys":["name"]}}},"ActivityParty":{".class":"SymbolTableNode","kind":"Gdef","node":{".class":"TypeInfo","_promote":[],"abstract_attributes":[],"alt_promote":null,"bases":["typing._TypedDict"],"dataclass_transform_spec":null,"declared_metaclass":null,"defn":{".class":"ClassDef","fullname":"nextcord.types.activity.ActivityParty","name":"ActivityParty","type_vars":[]},"deletable_attributes":[],"flags":[],"fullname":"nextcord.types.activity.ActivityParty","has_param_spec_type":false,"metaclass_type":null,"metadata":{},"module_name":"nextcord.types.activity","mro":["nextcord.types.activity.ActivityParty","typing._TypedDict","typing.Mapping","typing.Collection","typing.Iterable","typing.Container","builtins.object"],"names":{".class":"SymbolTable"},"self_type":null,"slots":null,"tuple_type":null,"type_vars":[],"typeddict_type":{".class":"TypedDictType","fallback":"typing._TypedDict","items":[["id","builtins.str"],["size",{".class":"Instance","args":["builtins.int"],"type_ref":"builtins.list"}]],"required_keys":[]}}},"ActivitySecrets":{".class":"SymbolTableNode","kind":"Gdef","node":{".class":"TypeInfo","_promote":[],"abstract_attributes":[],"alt_promote":null,"bases":["typing._TypedDict"],"dataclass_transform_spec":null,"declared_metaclass":null,"defn":{".class":"ClassDef","fullname":"nextcord.types.activity.ActivitySecrets","name":"ActivitySecrets","type_vars":[]},"deletable_attributes":[],"flags":[],"fullname":"nextcord.types.activity.ActivitySecrets","has_param_spec_type":false,"metaclass_type":null,"metadata":{},"module_name":"nextcord.types.activity","mro":["nextcord.types.activity.ActivitySecrets","typing._TypedDict","typing.Mapping","typing.Collection","typing.Iterable","typing.Container","builtins.object"],"names":{".class":"SymbolTable"},"self_type":null,"slots":null,"tuple_type":null,"type_vars":[],"typeddict_type":{".class":"TypedDictType","fallback":"typing._TypedDict","items":[["join","builtins.str"],["spectate","builtins.str"],["match","builtins.str"]],"required_keys":[]}}},"ActivityTimestamps":{".class":"SymbolTableNode","kind":"Gdef","node":{".class":"TypeInfo","_promote":[],"abstract_attributes":[],"alt_promote":null,"bases":["typing._TypedDict"],"dataclass_transform_spec":null,"declared_metaclass":null,"defn":{".class":"ClassDef","fullname":"nextcord.types.activity.ActivityTimestamps","name":"ActivityTimestamps","type_vars":[]},"deletable_attributes":[],"flags":[],"fullname":"nextcord.types.activity.ActivityTimestamps","has_param_spec_type":false,"metaclass_type":null,"metadata":{},"module_name":"nextcord.types.activity","mro":["nextcord.types.activity.ActivityTimestamps","typing._TypedDict","typing.Mapping","typing.Collection","typing.Iterable","typing.Container","builtins.object"],"names":{".class":"SymbolTable"},"self_type":null,"slots":null,"tuple_type":null,"type_vars":[],"typeddict_type":{".class":"TypedDictType","fallback":"typing._TypedDict","items":[["start","builtins.int"],["end","builtins.int"]],"required_keys":[]}}},"ActivityType":{".class":"SymbolTableNode","kind":"Gdef","node":{".class":"TypeAlias","alias_tvars":[],"column":0,"fullname":"nextcord.types.activity.ActivityType","line":63,"no_args":false,"normalized":false,"target":{".class":"UnionType","items":[{".class":"LiteralType","fallback":"builtins.int","value":0},{".class":"LiteralType","fallback":"builtins.int","value":1},{".class":"LiteralType","fallback":"builtins.int","value":2},{".class":"LiteralType","fallback":"builtins.int","value":4},{".class":"LiteralType","fallback":"builtins.int","value":5}]}}},"ClientStatus":{".class":"SymbolTableNode","kind":"Gdef","node":{".class":"TypeInfo","_promote":[],"abstract_attributes":[],"alt_promote":null,"bases":["typing._TypedDict"],"dataclass_transform_spec":null,"declared_metaclass":null,"defn":{".class":"ClassDef","fullname":"nextcord.types.activity.ClientStatus","name":"ClientStatus","type_vars":[]},"deletable_attributes":[],"flags":[],"fullname":"nextcord.types.activity.ClientStatus","has_param_spec_type":false,"metaclass_type":null,"metadata":{},"module_name":"nextcord.types.activity","mro":["nextcord.types.activity.ClientStatus","typing._TypedDict","typing.Mapping","typing.Collection","typing.Iterable","typing.Container","builtins.object"],"names":{".class":"SymbolTable"},"self_type":null,"slots":null,"tuple_type":null,"type_vars":[],"typeddict_type":{".class":"TypedDictType","fallback":"typing._TypedDict","items":[["desktop","builtins.str"],["mobile","builtins.str"],["web","builtins.str"]],"required_keys":[]}}},"List":{".class":"SymbolTableNode","cross_ref":"typing.List","kind":"Gdef"},"Literal":{".class":"SymbolTableNode","cross_ref":"typing.Literal","kind":"Gdef"},"NotRequired":{".class":"SymbolTableNode","cross_ref":"typing.NotRequired","kind":"Gdef"},"Optional":{".class":"SymbolTableNode","cross_ref":"typing.Optional","kind":"Gdef"},"PartialPresenceUpdate":{".class":"SymbolTableNode","kind":"Gdef","node":{".class":"TypeInfo","_promote":[],"abstract_attributes":[],"alt_promote":null,"bases":["typing._TypedDict"],"dataclass_transform_spec":null,"declared_metaclass":null,"defn":{".class":"ClassDef","fullname":"nextcord.types.activity.PartialPresenceUpdate","name":"PartialPresenceUpdate","type_vars":[]},"deletable_attributes":[],"flags":[],"fullname":"nextcord.types.activity.PartialPresenceUpdate","has_param_spec_type":false,"metaclass_type":null,"metadata":{},"module_name":"nextcord.types.activity","mro":["nextcord.types.activity.PartialPresenceUpdate","typing._TypedDict","typing.Mapping","typing.Collection","typing.Iterable","typing.Container","builtins.object"],"names":{".class":"SymbolTable"},"self_type":null,"slots":null,"tuple_type":null,"type_vars":[],"typeddict_type":{".class":"TypedDictType","fallback":"typing._TypedDict","items":[["user",{".class":"TypeAliasType","args":[],"type_ref":"nextcord.types.user.PartialUser"}],["guild_id",{".class":"TypeAliasType","args":[],"type_ref":"nextcord.types.snowflake.Snowflake"}],["status",{".class":"TypeAliasType","args":[],"type_ref":"nextcord.types.activity.StatusType"}],["activities",{".class":"Instance","args":[{".class":"TypeAliasType","args":[],"type_ref":"nextcord.types.activity.Activity"}],"type_ref":"builtins.list"}],["client_status",{".class":"TypeAliasType","args":[],"type_ref":"nextcord.types.activity.ClientStatus"}]],"required_keys":["activities","client_status","guild_id","status","user"]}}},"PartialUser":{".class":"SymbolTableNode","cross_ref":"nextcord.types.user.PartialUser","kind":"Gdef"},"SendableActivity":{".class":"SymbolTableNode","kind":"Gdef","node":{".class":"TypeInfo","_promote":[],"abstract_attributes":[],"alt_promote":null,"bases":["typing._TypedDict"],"dataclass_transform_spec":null,"declared_metaclass":null,"defn":{".class":"ClassDef","fullname":"nextcord.types.activity.SendableActivity","name":"SendableActivity","type_vars":[]},"deletable_attributes":[],"flags":[],"fullname":"nextcord.types.activity.SendableActivity","has_param_spec_type":false,"metaclass_type":null,"metadata":{},"module_name":"nextcord.types.activity","mro":["nextcord.types.activity.SendableActivity","typing._TypedDict","typing.Mapping","typing.Collection","typing.Iterable","typing.Container","builtins.object"],"names":{".class":"SymbolTable"},"self_type":null,"slots":null,"tuple_type":null,"type_vars":[],"typeddict_type":{".class":"TypedDictType","fallback":"typing._TypedDict","items":[["name","builtins.str"],["type",{".class":"TypeAliasType","args":[],"type_ref":"nextcord.types.activity.ActivityType"}],["url",{".class":"UnionType","items":["builtins.str",{".class":"NoneType"}]}]],"required_keys":["name","type"]}}},"Snowflake":{".class":"SymbolTableNode","cross_ref":"nextcord.types.snowflake.Snowflake","kind":"Gdef"},"StatusType":{".class":"SymbolTableNode","kind":"Gdef","node":{".class":"TypeAlias","alias_tvars":[],"column":0,"fullname":"nextcord.types.activity.StatusType","line":12,"no_args":false,"normalized":false,"target":{".class":"UnionType","items":[{".class":"LiteralType","fallback":"builtins.str","value":"idle"},{".class":"LiteralType","fallback":"builtins.str","value":"dnd"},{".class":"LiteralType","fallback":"builtins.str","value":"online"},{".class":"LiteralType","fallback":"builtins.str","value":"offline"}]}}},"TypedDict":{".class":"SymbolTableNode","cross_ref":"typing.TypedDict","kind":"Gdef"},"_BaseActivity":{".class":"SymbolTableNode","kind":"Gdef","node":{".class":"TypeInfo","_promote":[],"abstract_attributes":[],"alt_promote":null,"bases":["typing._TypedDict"],"dataclass_transform_spec":null,"declared_metaclass":null,"defn":{".class":"ClassDef","fullname":"nextcord.types.activity._BaseActivity","name":"_BaseActivity","type_vars":[]},"deletable_attributes":[],"flags":[],"fullname":"nextcord.types.activity._BaseActivity","has_param_spec_type":false,"metaclass_type":null,"metadata":{},"module_name":"nextcord.types.activity","mro":["nextcord.types.activity._BaseActivity","typing._TypedDict","typing.Mapping","typing.Collection","typing.Iterable","typing.Container","builtins.object"],"names":{".class":"SymbolTable"},"self_type":null,"slots":null,"tuple_type":null,"type_vars":[],"typeddict_type":{".class":"TypedDictType","fallback":"typing._TypedDict","items":[["name","builtins.str"],["type",{".class":"TypeAliasType","args":[],"type_ref":"nextcord.types.activity.ActivityType"}],["url",{".class":"UnionType","items":["builtins.str",{".class":"NoneType"}]}],["created_at","builtins.int"]],"required_keys":["created_at","name","type"]}}},"__annotations__":{".class":"SymbolTableNode","kind":"Gdef","node":{".class":"Var","flags":["is_ready"],"fullname":"nextcord.types.activity.__annotations__","name":"__annotations__","type":{".class":"Instance","args":["builtins.str",{".class":"AnyType","missing_import_name":null,"source_any":null,"type_of_any":6}],"type_ref":"builtins.dict"}}},"__doc__":{".class":"SymbolTableNode","kind":"Gdef","node":{".class":"Var","flags":["is_ready"],"fullname":"nextcord.types.activity.__doc__","name":"__doc__","type":"builtins.str"}},"__file__":{".class":"SymbolTableNode","kind":"Gdef","node":{".class":"Var","flags":["is_ready"],"fullname":"nextcord.types.activity.__file__","name":"__file__","type":"builtins.str"}},"__name__":{".class":"SymbolTableNode","kind":"Gdef","node":{".class":"Var","flags":["is_ready"],"fullname":"nextcord.types.activity.__name__","name":"__name__","type":"builtins.str"}},"__package__":{".class":"SymbolTableNode","kind":"Gdef","node":{".class":"Var","flags":["is_ready"],"fullname":"nextcord.types.activity.__package__","name":"__package__","type":"builtins.str"}},"annotations":{".class":"SymbolTableNode","cross_ref":"__future__.annotations","kind":"Gdef"}},"path":"c:\\Python312\\Lib\\site-packages\\nextcord\\types\\activity.py"}