{".class":"MypyFile","_fullname":"nextcord.types.guild","future_import_flags":[],"is_partial_stub_package":false,"is_stub":false,"names":{".class":"SymbolTable","Ban":{".class":"SymbolTableNode","kind":"Gdef","node":{".class":"TypeInfo","_promote":[],"abstract_attributes":[],"alt_promote":null,"bases":["typing._TypedDict"],"dataclass_transform_spec":null,"declared_metaclass":null,"defn":{".class":"ClassDef","fullname":"nextcord.types.guild.Ban","name":"Ban","type_vars":[]},"deletable_attributes":[],"flags":[],"fullname":"nextcord.types.guild.Ban","has_param_spec_type":false,"metaclass_type":null,"metadata":{},"module_name":"nextcord.types.guild","mro":["nextcord.types.guild.Ban","typing._TypedDict","typing.Mapping","typing.Collection","typing.Iterable","typing.Container","builtins.object"],"names":{".class":"SymbolTable"},"self_type":null,"slots":null,"tuple_type":null,"type_vars":[],"typeddict_type":{".class":"TypedDictType","fallback":"typing._TypedDict","items":[["reason",{".class":"UnionType","items":["builtins.str",{".class":"NoneType"}]}],["user",{".class":"TypeAliasType","args":[],"type_ref":"nextcord.types.user.User"}]],"required_keys":["reason","user"]}}},"ChannelPositionUpdate":{".class":"SymbolTableNode","kind":"Gdef","node":{".class":"TypeInfo","_promote":[],"abstract_attributes":[],"alt_promote":null,"bases":["typing._TypedDict"],"dataclass_transform_spec":null,"declared_metaclass":null,"defn":{".class":"ClassDef","fullname":"nextcord.types.guild.ChannelPositionUpdate","name":"ChannelPositionUpdate","type_vars":[]},"deletable_attributes":[],"flags":[],"fullname":"nextcord.types.guild.ChannelPositionUpdate","has_param_spec_type":false,"metaclass_type":null,"metadata":{},"module_name":"nextcord.types.guild","mro":["nextcord.types.guild.ChannelPositionUpdate","typing._TypedDict","typing.Mapping","typing.Collection","typing.Iterable","typing.Container","builtins.object"],"names":{".class":"SymbolTable"},"self_type":null,"slots":null,"tuple_type":null,"type_vars":[],"typeddict_type":{".class":"TypedDictType","fallback":"typing._TypedDict","items":[["id",{".class":"TypeAliasType","args":[],"type_ref":"nextcord.types.snowflake.Snowflake"}],["position",{".class":"UnionType","items":["builtins.int",{".class":"NoneType"}]}],["lock_permissions",{".class":"UnionType","items":["builtins.bool",{".class":"NoneType"}]}],["parent_id",{".class":"UnionType","items":["builtins.str","builtins.int",{".class":"NoneType"}]}]],"required_keys":["id","lock_permissions","parent_id","position"]}}},"DefaultMessageNotificationLevel":{".class":"SymbolTableNode","kind":"Gdef","node":{".class":"TypeAlias","alias_tvars":[],"column":0,"fullname":"nextcord.types.guild.DefaultMessageNotificationLevel","line":31,"no_args":false,"normalized":false,"target":{".class":"UnionType","items":[{".class":"LiteralType","fallback":"builtins.int","value":0},{".class":"LiteralType","fallback":"builtins.int","value":1}]}}},"Emoji":{".class":"SymbolTableNode","cross_ref":"nextcord.types.emoji.Emoji","kind":"Gdef"},"ExplicitContentFilterLevel":{".class":"SymbolTableNode","kind":"Gdef","node":{".class":"TypeAlias","alias_tvars":[],"column":0,"fullname":"nextcord.types.guild.ExplicitContentFilterLevel","line":32,"no_args":false,"normalized":false,"target":{".class":"UnionType","items":[{".class":"LiteralType","fallback":"builtins.int","value":0},{".class":"LiteralType","fallback":"builtins.int","value":1},{".class":"LiteralType","fallback":"builtins.int","value":2}]}}},"Guild":{".class":"SymbolTableNode","kind":"Gdef","node":{".class":"TypeInfo","_promote":[],"abstract_attributes":[],"alt_promote":null,"bases":["typing._TypedDict"],"dataclass_transform_spec":null,"declared_metaclass":null,"defn":{".class":"ClassDef","fullname":"nextcord.types.guild.Guild","name":"Guild","type_vars":[]},"deletable_attributes":[],"flags":[],"fullname":"nextcord.types.guild.Guild","has_param_spec_type":false,"metaclass_type":null,"metadata":{},"module_name":"nextcord.types.guild","mro":["nextcord.types.guild.Guild","typing._TypedDict","typing.Mapping","typing.Collection","typing.Iterable","typing.Container","builtins.object"],"names":{".class":"SymbolTable"},"self_type":null,"slots":null,"tuple_type":null,"type_vars":[],"typeddict_type":{".class":"TypedDictType","fallback":"typing._TypedDict","items":[["id",{".class":"TypeAliasType","args":[],"type_ref":"nextcord.types.snowflake.Snowflake"}],["unavailable","builtins.bool"],["name","builtins.str"],["icon",{".class":"UnionType","items":["builtins.str",{".class":"NoneType"}]}],["splash",{".class":"UnionType","items":["builtins.str",{".class":"NoneType"}]}],["discovery_splash",{".class":"UnionType","items":["builtins.str",{".class":"NoneType"}]}],["emojis",{".class":"Instance","args":[{".class":"TypeAliasType","args":[],"type_ref":"nextcord.types.emoji.Emoji"}],"type_ref":"builtins.list"}],["features",{".class":"Instance","args":[{".class":"TypeAliasType","args":[],"type_ref":"nextcord.types.guild.GuildFeature"}],"type_ref":"builtins.list"}],["description",{".class":"UnionType","items":["builtins.str",{".class":"NoneType"}]}],["stickers",{".class":"Instance","args":[{".class":"TypeAliasType","args":[],"type_ref":"nextcord.types.sticker.GuildSticker"}],"type_ref":"builtins.list"}],["owner_id",{".class":"TypeAliasType","args":[],"type_ref":"nextcord.types.snowflake.Snowflake"}],["region","builtins.str"],["afk_channel_id",{".class":"UnionType","items":["builtins.str","builtins.int",{".class":"NoneType"}]}],["afk_timeout","builtins.int"],["verification_level",{".class":"TypeAliasType","args":[],"type_ref":"nextcord.types.guild.VerificationLevel"}],["default_message_notifications",{".class":"TypeAliasType","args":[],"type_ref":"nextcord.types.guild.DefaultMessageNotificationLevel"}],["explicit_content_filter",{".class":"TypeAliasType","args":[],"type_ref":"nextcord.types.guild.ExplicitContentFilterLevel"}],["roles",{".class":"Instance","args":[{".class":"TypeAliasType","args":[],"type_ref":"nextcord.types.role.Role"}],"type_ref":"builtins.list"}],["mfa_level",{".class":"TypeAliasType","args":[],"type_ref":"nextcord.types.guild.MFALevel"}],["nsfw_level",{".class":"TypeAliasType","args":[],"type_ref":"nextcord.types.guild.NSFWLevel"}],["application_id",{".class":"UnionType","items":["builtins.str","builtins.int",{".class":"NoneType"}]}],["system_channel_id",{".class":"UnionType","items":["builtins.str","builtins.int",{".class":"NoneType"}]}],["system_channel_flags","builtins.int"],["rules_channel_id",{".class":"UnionType","items":["builtins.str","builtins.int",{".class":"NoneType"}]}],["vanity_url_code",{".class":"UnionType","items":["builtins.str",{".class":"NoneType"}]}],["banner",{".class":"UnionType","items":["builtins.str",{".class":"NoneType"}]}],["premium_tier",{".class":"TypeAliasType","args":[],"type_ref":"nextcord.types.guild.PremiumTier"}],["preferred_locale","builtins.str"],["public_updates_channel_id",{".class":"UnionType","items":["builtins.str","builtins.int",{".class":"NoneType"}]}],["guild_scheduled_events",{".class":"UnionType","items":[{".class":"Instance","args":[{".class":"TypeAliasType","args":[],"type_ref":"nextcord.types.scheduled_events.ScheduledEvent"}],"type_ref":"builtins.list"},{".class":"NoneType"}]}],["icon_hash",{".class":"UnionType","items":["builtins.str",{".class":"NoneType"}]}],["owner","builtins.bool"],["permissions","builtins.str"],["widget_enabled","builtins.bool"],["widget_channel_id",{".class":"UnionType","items":["builtins.str","builtins.int",{".class":"NoneType"}]}],["joined_at",{".class":"UnionType","items":["builtins.str",{".class":"NoneType"}]}],["large","builtins.bool"],["member_count","builtins.int"],["voice_states",{".class":"Instance","args":[{".class":"TypeAliasType","args":[],"type_ref":"nextcord.types.voice.GuildVoiceState"}],"type_ref":"builtins.list"}],["members",{".class":"Instance","args":[{".class":"TypeAliasType","args":[],"type_ref":"nextcord.types.member.Member"}],"type_ref":"builtins.list"}],["channels",{".class":"Instance","args":[{".class":"TypeAliasType","args":[],"type_ref":"nextcord.types.channel.GuildChannel"}],"type_ref":"builtins.list"}],["presences",{".class":"Instance","args":[{".class":"TypeAliasType","args":[],"type_ref":"nextcord.types.activity.PartialPresenceUpdate"}],"type_ref":"builtins.list"}],["threads",{".class":"Instance","args":[{".class":"TypeAliasType","args":[],"type_ref":"nextcord.types.threads.Thread"}],"type_ref":"builtins.list"}],["max_presences",{".class":"UnionType","items":["builtins.int",{".class":"NoneType"}]}],["max_members","builtins.int"],["premium_subscription_count","builtins.int"],["max_video_channel_users","builtins.int"],["max_stage_video_channel_users","builtins.int"],["premium_progress_bar_enabled",{".class":"UnionType","items":["builtins.bool",{".class":"NoneType"}]}],["safety_alerts_channel_id",{".class":"UnionType","items":["builtins.str","builtins.int",{".class":"NoneType"}]}]],"required_keys":["afk_channel_id","afk_timeout","application_id","banner","default_message_notifications","description","discovery_splash","emojis","explicit_content_filter","features","guild_scheduled_events","icon","id","mfa_level","name","nsfw_level","owner_id","preferred_locale","premium_progress_bar_enabled","premium_tier","public_updates_channel_id","region","roles","rules_channel_id","safety_alerts_channel_id","splash","stickers","system_channel_flags","system_channel_id","vanity_url_code","verification_level"]}}},"GuildChannel":{".class":"SymbolTableNode","cross_ref":"nextcord.types.channel.GuildChannel","kind":"Gdef"},"GuildFeature":{".class":"SymbolTableNode","kind":"Gdef","node":{".class":"TypeAlias","alias_tvars":[],"column":0,"fullname":"nextcord.types.guild.GuildFeature","line":37,"no_args":false,"normalized":false,"target":{".class":"UnionType","items":[{".class":"LiteralType","fallback":"builtins.str","value":"AUTO_MODERATION"},{".class":"LiteralType","fallback":"builtins.str","value":"ANIMATED_BANNER"},{".class":"LiteralType","fallback":"builtins.str","value":"ANIMATED_ICON"},{".class":"LiteralType","fallback":"builtins.str","value":"APPLICATION_COMMAND_PERMISSIONS_V2"},{".class":"LiteralType","fallback":"builtins.str","value":"BANNER"},{".class":"LiteralType","fallback":"builtins.str","value":"COMMUNITY"},{".class":"LiteralType","fallback":"builtins.str","value":"DEVELOPER_SUPPORT_SERVER"},{".class":"LiteralType","fallback":"builtins.str","value":"DISCOVERABLE"},{".class":"LiteralType","fallback":"builtins.str","value":"FEATURABLE"},{".class":"LiteralType","fallback":"builtins.str","value":"INVITES_DISABLED"},{".class":"LiteralType","fallback":"builtins.str","value":"INVITE_SPLASH"},{".class":"LiteralType","fallback":"builtins.str","value":"MEMBER_VERIFICATION_GATE_ENABLED"},{".class":"LiteralType","fallback":"builtins.str","value":"MONETIZATION_ENABLED"},{".class":"LiteralType","fallback":"builtins.str","value":"MORE_STICKERS"},{".class":"LiteralType","fallback":"builtins.str","value":"NEWS"},{".class":"LiteralType","fallback":"builtins.str","value":"PARTNERED"},{".class":"LiteralType","fallback":"builtins.str","value":"PREVIEW_ENABLED"},{".class":"LiteralType","fallback":"builtins.str","value":"RAID_ALERTS_DISABLED"},{".class":"LiteralType","fallback":"builtins.str","value":"ROLE_ICONS"},{".class":"LiteralType","fallback":"builtins.str","value":"TICKETED_EVENTS_ENABLED"},{".class":"LiteralType","fallback":"builtins.str","value":"VANITY_URL"},{".class":"LiteralType","fallback":"builtins.str","value":"VERIFIED"},{".class":"LiteralType","fallback":"builtins.str","value":"VIP_REGIONS"},{".class":"LiteralType","fallback":"builtins.str","value":"WELCOME_SCREEN_ENABLED"}]}}},"GuildPreview":{".class":"SymbolTableNode","kind":"Gdef","node":{".class":"TypeInfo","_promote":[],"abstract_attributes":[],"alt_promote":null,"bases":["typing._TypedDict"],"dataclass_transform_spec":null,"declared_metaclass":null,"defn":{".class":"ClassDef","fullname":"nextcord.types.guild.GuildPreview","name":"GuildPreview","type_vars":[]},"deletable_attributes":[],"flags":[],"fullname":"nextcord.types.guild.GuildPreview","has_param_spec_type":false,"metaclass_type":null,"metadata":{},"module_name":"nextcord.types.guild","mro":["nextcord.types.guild.GuildPreview","typing._TypedDict","typing.Mapping","typing.Collection","typing.Iterable","typing.Container","builtins.object"],"names":{".class":"SymbolTable"},"self_type":null,"slots":null,"tuple_type":null,"type_vars":[],"typeddict_type":{".class":"TypedDictType","fallback":"typing._TypedDict","items":[["approximate_member_count","builtins.int"],["approximate_presence_count","builtins.int"],["id",{".class":"TypeAliasType","args":[],"type_ref":"nextcord.types.snowflake.Snowflake"}],["unavailable","builtins.bool"],["name","builtins.str"],["icon",{".class":"UnionType","items":["builtins.str",{".class":"NoneType"}]}],["splash",{".class":"UnionType","items":["builtins.str",{".class":"NoneType"}]}],["discovery_splash",{".class":"UnionType","items":["builtins.str",{".class":"NoneType"}]}],["emojis",{".class":"Instance","args":[{".class":"TypeAliasType","args":[],"type_ref":"nextcord.types.emoji.Emoji"}],"type_ref":"builtins.list"}],["features",{".class":"Instance","args":[{".class":"TypeAliasType","args":[],"type_ref":"nextcord.types.guild.GuildFeature"}],"type_ref":"builtins.list"}],["description",{".class":"UnionType","items":["builtins.str",{".class":"NoneType"}]}],["stickers",{".class":"Instance","args":[{".class":"TypeAliasType","args":[],"type_ref":"nextcord.types.sticker.GuildSticker"}],"type_ref":"builtins.list"}]],"required_keys":["approximate_member_count","approximate_presence_count","description","discovery_splash","emojis","features","icon","id","name","splash","stickers"]}}},"GuildPrune":{".class":"SymbolTableNode","kind":"Gdef","node":{".class":"TypeInfo","_promote":[],"abstract_attributes":[],"alt_promote":null,"bases":["typing._TypedDict"],"dataclass_transform_spec":null,"declared_metaclass":null,"defn":{".class":"ClassDef","fullname":"nextcord.types.guild.GuildPrune","name":"GuildPrune","type_vars":[]},"deletable_attributes":[],"flags":[],"fullname":"nextcord.types.guild.GuildPrune","has_param_spec_type":false,"metaclass_type":null,"metadata":{},"module_name":"nextcord.types.guild","mro":["nextcord.types.guild.GuildPrune","typing._TypedDict","typing.Mapping","typing.Collection","typing.Iterable","typing.Container","builtins.object"],"names":{".class":"SymbolTable"},"self_type":null,"slots":null,"tuple_type":null,"type_vars":[],"typeddict_type":{".class":"TypedDictType","fallback":"typing._TypedDict","items":[["pruned",{".class":"UnionType","items":["builtins.int",{".class":"NoneType"}]}]],"required_keys":["pruned"]}}},"GuildSticker":{".class":"SymbolTableNode","cross_ref":"nextcord.types.sticker.GuildSticker","kind":"Gdef"},"GuildVoiceState":{".class":"SymbolTableNode","cross_ref":"nextcord.types.voice.GuildVoiceState","kind":"Gdef"},"GuildWithCounts":{".class":"SymbolTableNode","kind":"Gdef","node":{".class":"TypeInfo","_promote":[],"abstract_attributes":[],"alt_promote":null,"bases":["typing._TypedDict"],"dataclass_transform_spec":null,"declared_metaclass":null,"defn":{".class":"ClassDef","fullname":"nextcord.types.guild.GuildWithCounts","name":"GuildWithCounts","type_vars":[]},"deletable_attributes":[],"flags":[],"fullname":"nextcord.types.guild.GuildWithCounts","has_param_spec_type":false,"metaclass_type":null,"metadata":{},"module_name":"nextcord.types.guild","mro":["nextcord.types.guild.GuildWithCounts","typing._TypedDict","typing.Mapping","typing.Collection","typing.Iterable","typing.Container","builtins.object"],"names":{".class":"SymbolTable"},"self_type":null,"slots":null,"tuple_type":null,"type_vars":[],"typeddict_type":{".class":"TypedDictType","fallback":"typing._TypedDict","items":[["approximate_member_count","builtins.int"],["approximate_presence_count","builtins.int"],["id",{".class":"TypeAliasType","args":[],"type_ref":"nextcord.types.snowflake.Snowflake"}],["unavailable","builtins.bool"],["name","builtins.str"],["icon",{".class":"UnionType","items":["builtins.str",{".class":"NoneType"}]}],["splash",{".class":"UnionType","items":["builtins.str",{".class":"NoneType"}]}],["discovery_splash",{".class":"UnionType","items":["builtins.str",{".class":"NoneType"}]}],["emojis",{".class":"Instance","args":[{".class":"TypeAliasType","args":[],"type_ref":"nextcord.types.emoji.Emoji"}],"type_ref":"builtins.list"}],["features",{".class":"Instance","args":[{".class":"TypeAliasType","args":[],"type_ref":"nextcord.types.guild.GuildFeature"}],"type_ref":"builtins.list"}],["description",{".class":"UnionType","items":["builtins.str",{".class":"NoneType"}]}],["stickers",{".class":"Instance","args":[{".class":"TypeAliasType","args":[],"type_ref":"nextcord.types.sticker.GuildSticker"}],"type_ref":"builtins.list"}],["owner_id",{".class":"TypeAliasType","args":[],"type_ref":"nextcord.types.snowflake.Snowflake"}],["region","builtins.str"],["afk_channel_id",{".class":"UnionType","items":["builtins.str","builtins.int",{".class":"NoneType"}]}],["afk_timeout","builtins.int"],["verification_level",{".class":"TypeAliasType","args":[],"type_ref":"nextcord.types.guild.VerificationLevel"}],["default_message_notifications",{".class":"TypeAliasType","args":[],"type_ref":"nextcord.types.guild.DefaultMessageNotificationLevel"}],["explicit_content_filter",{".class":"TypeAliasType","args":[],"type_ref":"nextcord.types.guild.ExplicitContentFilterLevel"}],["roles",{".class":"Instance","args":[{".class":"TypeAliasType","args":[],"type_ref":"nextcord.types.role.Role"}],"type_ref":"builtins.list"}],["mfa_level",{".class":"TypeAliasType","args":[],"type_ref":"nextcord.types.guild.MFALevel"}],["nsfw_level",{".class":"TypeAliasType","args":[],"type_ref":"nextcord.types.guild.NSFWLevel"}],["application_id",{".class":"UnionType","items":["builtins.str","builtins.int",{".class":"NoneType"}]}],["system_channel_id",{".class":"UnionType","items":["builtins.str","builtins.int",{".class":"NoneType"}]}],["system_channel_flags","builtins.int"],["rules_channel_id",{".class":"UnionType","items":["builtins.str","builtins.int",{".class":"NoneType"}]}],["vanity_url_code",{".class":"UnionType","items":["builtins.str",{".class":"NoneType"}]}],["banner",{".class":"UnionType","items":["builtins.str",{".class":"NoneType"}]}],["premium_tier",{".class":"TypeAliasType","args":[],"type_ref":"nextcord.types.guild.PremiumTier"}],["preferred_locale","builtins.str"],["public_updates_channel_id",{".class":"UnionType","items":["builtins.str","builtins.int",{".class":"NoneType"}]}],["guild_scheduled_events",{".class":"UnionType","items":[{".class":"Instance","args":[{".class":"TypeAliasType","args":[],"type_ref":"nextcord.types.scheduled_events.ScheduledEvent"}],"type_ref":"builtins.list"},{".class":"NoneType"}]}],["icon_hash",{".class":"UnionType","items":["builtins.str",{".class":"NoneType"}]}],["owner","builtins.bool"],["permissions","builtins.str"],["widget_enabled","builtins.bool"],["widget_channel_id",{".class":"UnionType","items":["builtins.str","builtins.int",{".class":"NoneType"}]}],["joined_at",{".class":"UnionType","items":["builtins.str",{".class":"NoneType"}]}],["large","builtins.bool"],["member_count","builtins.int"],["voice_states",{".class":"Instance","args":[{".class":"TypeAliasType","args":[],"type_ref":"nextcord.types.voice.GuildVoiceState"}],"type_ref":"builtins.list"}],["members",{".class":"Instance","args":[{".class":"TypeAliasType","args":[],"type_ref":"nextcord.types.member.Member"}],"type_ref":"builtins.list"}],["channels",{".class":"Instance","args":[{".class":"TypeAliasType","args":[],"type_ref":"nextcord.types.channel.GuildChannel"}],"type_ref":"builtins.list"}],["presences",{".class":"Instance","args":[{".class":"TypeAliasType","args":[],"type_ref":"nextcord.types.activity.PartialPresenceUpdate"}],"type_ref":"builtins.list"}],["threads",{".class":"Instance","args":[{".class":"TypeAliasType","args":[],"type_ref":"nextcord.types.threads.Thread"}],"type_ref":"builtins.list"}],["max_presences",{".class":"UnionType","items":["builtins.int",{".class":"NoneType"}]}],["max_members","builtins.int"],["premium_subscription_count","builtins.int"],["max_video_channel_users","builtins.int"],["max_stage_video_channel_users","builtins.int"],["premium_progress_bar_enabled",{".class":"UnionType","items":["builtins.bool",{".class":"NoneType"}]}],["safety_alerts_channel_id",{".class":"UnionType","items":["builtins.str","builtins.int",{".class":"NoneType"}]}]],"required_keys":["afk_channel_id","afk_timeout","application_id","approximate_member_count","approximate_presence_count","banner","default_message_notifications","description","discovery_splash","emojis","explicit_content_filter","features","guild_scheduled_events","icon","id","mfa_level","name","nsfw_level","owner_id","preferred_locale","premium_progress_bar_enabled","premium_tier","public_updates_channel_id","region","roles","rules_channel_id","safety_alerts_channel_id","splash","stickers","system_channel_flags","system_channel_id","vanity_url_code","verification_level"]}}},"InviteGuild":{".class":"SymbolTableNode","kind":"Gdef","node":{".class":"TypeInfo","_promote":[],"abstract_attributes":[],"alt_promote":null,"bases":["typing._TypedDict"],"dataclass_transform_spec":null,"declared_metaclass":null,"defn":{".class":"ClassDef","fullname":"nextcord.types.guild.InviteGuild","name":"InviteGuild","type_vars":[]},"deletable_attributes":[],"flags":[],"fullname":"nextcord.types.guild.InviteGuild","has_param_spec_type":false,"metaclass_type":null,"metadata":{},"module_name":"nextcord.types.guild","mro":["nextcord.types.guild.InviteGuild","typing._TypedDict","typing.Mapping","typing.Collection","typing.Iterable","typing.Container","builtins.object"],"names":{".class":"SymbolTable"},"self_type":null,"slots":null,"tuple_type":null,"type_vars":[],"typeddict_type":{".class":"TypedDictType","fallback":"typing._TypedDict","items":[["id",{".class":"TypeAliasType","args":[],"type_ref":"nextcord.types.snowflake.Snowflake"}],["unavailable","builtins.bool"],["name","builtins.str"],["icon",{".class":"UnionType","items":["builtins.str",{".class":"NoneType"}]}],["splash",{".class":"UnionType","items":["builtins.str",{".class":"NoneType"}]}],["discovery_splash",{".class":"UnionType","items":["builtins.str",{".class":"NoneType"}]}],["emojis",{".class":"Instance","args":[{".class":"TypeAliasType","args":[],"type_ref":"nextcord.types.emoji.Emoji"}],"type_ref":"builtins.list"}],["features",{".class":"Instance","args":[{".class":"TypeAliasType","args":[],"type_ref":"nextcord.types.guild.GuildFeature"}],"type_ref":"builtins.list"}],["description",{".class":"UnionType","items":["builtins.str",{".class":"NoneType"}]}],["stickers",{".class":"Instance","args":[{".class":"TypeAliasType","args":[],"type_ref":"nextcord.types.sticker.GuildSticker"}],"type_ref":"builtins.list"}],["owner_id",{".class":"TypeAliasType","args":[],"type_ref":"nextcord.types.snowflake.Snowflake"}],["region","builtins.str"],["afk_channel_id",{".class":"UnionType","items":["builtins.str","builtins.int",{".class":"NoneType"}]}],["afk_timeout","builtins.int"],["verification_level",{".class":"TypeAliasType","args":[],"type_ref":"nextcord.types.guild.VerificationLevel"}],["default_message_notifications",{".class":"TypeAliasType","args":[],"type_ref":"nextcord.types.guild.DefaultMessageNotificationLevel"}],["explicit_content_filter",{".class":"TypeAliasType","args":[],"type_ref":"nextcord.types.guild.ExplicitContentFilterLevel"}],["roles",{".class":"Instance","args":[{".class":"TypeAliasType","args":[],"type_ref":"nextcord.types.role.Role"}],"type_ref":"builtins.list"}],["mfa_level",{".class":"TypeAliasType","args":[],"type_ref":"nextcord.types.guild.MFALevel"}],["nsfw_level",{".class":"TypeAliasType","args":[],"type_ref":"nextcord.types.guild.NSFWLevel"}],["application_id",{".class":"UnionType","items":["builtins.str","builtins.int",{".class":"NoneType"}]}],["system_channel_id",{".class":"UnionType","items":["builtins.str","builtins.int",{".class":"NoneType"}]}],["system_channel_flags","builtins.int"],["rules_channel_id",{".class":"UnionType","items":["builtins.str","builtins.int",{".class":"NoneType"}]}],["vanity_url_code",{".class":"UnionType","items":["builtins.str",{".class":"NoneType"}]}],["banner",{".class":"UnionType","items":["builtins.str",{".class":"NoneType"}]}],["premium_tier",{".class":"TypeAliasType","args":[],"type_ref":"nextcord.types.guild.PremiumTier"}],["preferred_locale","builtins.str"],["public_updates_channel_id",{".class":"UnionType","items":["builtins.str","builtins.int",{".class":"NoneType"}]}],["guild_scheduled_events",{".class":"UnionType","items":[{".class":"Instance","args":[{".class":"TypeAliasType","args":[],"type_ref":"nextcord.types.scheduled_events.ScheduledEvent"}],"type_ref":"builtins.list"},{".class":"NoneType"}]}],["icon_hash",{".class":"UnionType","items":["builtins.str",{".class":"NoneType"}]}],["owner","builtins.bool"],["permissions","builtins.str"],["widget_enabled","builtins.bool"],["widget_channel_id",{".class":"UnionType","items":["builtins.str","builtins.int",{".class":"NoneType"}]}],["joined_at",{".class":"UnionType","items":["builtins.str",{".class":"NoneType"}]}],["large","builtins.bool"],["member_count","builtins.int"],["voice_states",{".class":"Instance","args":[{".class":"TypeAliasType","args":[],"type_ref":"nextcord.types.voice.GuildVoiceState"}],"type_ref":"builtins.list"}],["members",{".class":"Instance","args":[{".class":"TypeAliasType","args":[],"type_ref":"nextcord.types.member.Member"}],"type_ref":"builtins.list"}],["channels",{".class":"Instance","args":[{".class":"TypeAliasType","args":[],"type_ref":"nextcord.types.channel.GuildChannel"}],"type_ref":"builtins.list"}],["presences",{".class":"Instance","args":[{".class":"TypeAliasType","args":[],"type_ref":"nextcord.types.activity.PartialPresenceUpdate"}],"type_ref":"builtins.list"}],["threads",{".class":"Instance","args":[{".class":"TypeAliasType","args":[],"type_ref":"nextcord.types.threads.Thread"}],"type_ref":"builtins.list"}],["max_presences",{".class":"UnionType","items":["builtins.int",{".class":"NoneType"}]}],["max_members","builtins.int"],["premium_subscription_count","builtins.int"],["max_video_channel_users","builtins.int"],["max_stage_video_channel_users","builtins.int"],["premium_progress_bar_enabled",{".class":"UnionType","items":["builtins.bool",{".class":"NoneType"}]}],["safety_alerts_channel_id",{".class":"UnionType","items":["builtins.str","builtins.int",{".class":"NoneType"}]}],["welcome_screen",{".class":"TypeAliasType","args":[],"type_ref":"nextcord.types.welcome_screen.WelcomeScreen"}]],"required_keys":["afk_channel_id","afk_timeout","application_id","banner","default_message_notifications","description","discovery_splash","emojis","explicit_content_filter","features","guild_scheduled_events","icon","id","mfa_level","name","nsfw_level","owner_id","preferred_locale","premium_progress_bar_enabled","premium_tier","public_updates_channel_id","region","roles","rules_channel_id","safety_alerts_channel_id","splash","stickers","system_channel_flags","system_channel_id","vanity_url_code","verification_level"]}}},"List":{".class":"SymbolTableNode","cross_ref":"typing.List","kind":"Gdef"},"Literal":{".class":"SymbolTableNode","cross_ref":"typing.Literal","kind":"Gdef"},"MFALevel":{".class":"SymbolTableNode","kind":"Gdef","node":{".class":"TypeAlias","alias_tvars":[],"column":0,"fullname":"nextcord.types.guild.MFALevel","line":33,"no_args":false,"normalized":false,"target":{".class":"UnionType","items":[{".class":"LiteralType","fallback":"builtins.int","value":0},{".class":"LiteralType","fallback":"builtins.int","value":1}]}}},"Member":{".class":"SymbolTableNode","cross_ref":"nextcord.types.member.Member","kind":"Gdef"},"NSFWLevel":{".class":"SymbolTableNode","kind":"Gdef","node":{".class":"TypeAlias","alias_tvars":[],"column":0,"fullname":"nextcord.types.guild.NSFWLevel","line":35,"no_args":false,"normalized":false,"target":{".class":"UnionType","items":[{".class":"LiteralType","fallback":"builtins.int","value":0},{".class":"LiteralType","fallback":"builtins.int","value":1},{".class":"LiteralType","fallback":"builtins.int","value":2},{".class":"LiteralType","fallback":"builtins.int","value":3}]}}},"NotRequired":{".class":"SymbolTableNode","cross_ref":"typing.NotRequired","kind":"Gdef"},"Optional":{".class":"SymbolTableNode","cross_ref":"typing.Optional","kind":"Gdef"},"PartialPresenceUpdate":{".class":"SymbolTableNode","cross_ref":"nextcord.types.activity.PartialPresenceUpdate","kind":"Gdef"},"PremiumTier":{".class":"SymbolTableNode","kind":"Gdef","node":{".class":"TypeAlias","alias_tvars":[],"column":0,"fullname":"nextcord.types.guild.PremiumTier","line":36,"no_args":false,"normalized":false,"target":{".class":"UnionType","items":[{".class":"LiteralType","fallback":"builtins.int","value":0},{".class":"LiteralType","fallback":"builtins.int","value":1},{".class":"LiteralType","fallback":"builtins.int","value":2},{".class":"LiteralType","fallback":"builtins.int","value":3}]}}},"Role":{".class":"SymbolTableNode","cross_ref":"nextcord.types.role.Role","kind":"Gdef"},"RolePositionUpdate":{".class":"SymbolTableNode","kind":"Gdef","node":{".class":"TypeInfo","_promote":[],"abstract_attributes":[],"alt_promote":null,"bases":["typing._TypedDict"],"dataclass_transform_spec":null,"declared_metaclass":null,"defn":{".class":"ClassDef","fullname":"nextcord.types.guild.RolePositionUpdate","name":"RolePositionUpdate","type_vars":[]},"deletable_attributes":[],"flags":[],"fullname":"nextcord.types.guild.RolePositionUpdate","has_param_spec_type":false,"metaclass_type":null,"metadata":{},"module_name":"nextcord.types.guild","mro":["nextcord.types.guild.RolePositionUpdate","typing._TypedDict","typing.Mapping","typing.Collection","typing.Iterable","typing.Container","builtins.object"],"names":{".class":"SymbolTable"},"self_type":null,"slots":null,"tuple_type":null,"type_vars":[],"typeddict_type":{".class":"TypedDictType","fallback":"typing._TypedDict","items":[["id",{".class":"TypeAliasType","args":[],"type_ref":"nextcord.types.snowflake.Snowflake"}],["position",{".class":"UnionType","items":["builtins.str","builtins.int",{".class":"NoneType"}]}]],"required_keys":["id"]}}},"ScheduledEvent":{".class":"SymbolTableNode","cross_ref":"nextcord.types.scheduled_events.ScheduledEvent","kind":"Gdef"},"Snowflake":{".class":"SymbolTableNode","cross_ref":"nextcord.types.snowflake.Snowflake","kind":"Gdef"},"Thread":{".class":"SymbolTableNode","cross_ref":"nextcord.types.threads.Thread","kind":"Gdef"},"TypedDict":{".class":"SymbolTableNode","cross_ref":"typing.TypedDict","kind":"Gdef"},"UnavailableGuild":{".class":"SymbolTableNode","kind":"Gdef","node":{".class":"TypeInfo","_promote":[],"abstract_attributes":[],"alt_promote":null,"bases":["typing._TypedDict"],"dataclass_transform_spec":null,"declared_metaclass":null,"defn":{".class":"ClassDef","fullname":"nextcord.types.guild.UnavailableGuild","name":"UnavailableGuild","type_vars":[]},"deletable_attributes":[],"flags":[],"fullname":"nextcord.types.guild.UnavailableGuild","has_param_spec_type":false,"metaclass_type":null,"metadata":{},"module_name":"nextcord.types.guild","mro":["nextcord.types.guild.UnavailableGuild","typing._TypedDict","typing.Mapping","typing.Collection","typing.Iterable","typing.Container","builtins.object"],"names":{".class":"SymbolTable"},"self_type":null,"slots":null,"tuple_type":null,"type_vars":[],"typeddict_type":{".class":"TypedDictType","fallback":"typing._TypedDict","items":[["id",{".class":"TypeAliasType","args":[],"type_ref":"nextcord.types.snowflake.Snowflake"}],["unavailable","builtins.bool"]],"required_keys":["id"]}}},"User":{".class":"SymbolTableNode","cross_ref":"nextcord.types.user.User","kind":"Gdef"},"VerificationLevel":{".class":"SymbolTableNode","kind":"Gdef","node":{".class":"TypeAlias","alias_tvars":[],"column":0,"fullname":"nextcord.types.guild.VerificationLevel","line":34,"no_args":false,"normalized":false,"target":{".class":"UnionType","items":[{".class":"LiteralType","fallback":"builtins.int","value":0},{".class":"LiteralType","fallback":"builtins.int","value":1},{".class":"LiteralType","fallback":"builtins.int","value":2},{".class":"LiteralType","fallback":"builtins.int","value":3},{".class":"LiteralType","fallback":"builtins.int","value":4}]}}},"WelcomeScreen":{".class":"SymbolTableNode","cross_ref":"nextcord.types.welcome_screen.WelcomeScreen","kind":"Gdef"},"_BaseGuildPreview":{".class":"SymbolTableNode","kind":"Gdef","node":{".class":"TypeInfo","_promote":[],"abstract_attributes":[],"alt_promote":null,"bases":["typing._TypedDict"],"dataclass_transform_spec":null,"declared_metaclass":null,"defn":{".class":"ClassDef","fullname":"nextcord.types.guild._BaseGuildPreview","name":"_BaseGuildPreview","type_vars":[]},"deletable_attributes":[],"flags":[],"fullname":"nextcord.types.guild._BaseGuildPreview","has_param_spec_type":false,"metaclass_type":null,"metadata":{},"module_name":"nextcord.types.guild","mro":["nextcord.types.guild._BaseGuildPreview","typing._TypedDict","typing.Mapping","typing.Collection","typing.Iterable","typing.Container","builtins.object"],"names":{".class":"SymbolTable"},"self_type":null,"slots":null,"tuple_type":null,"type_vars":[],"typeddict_type":{".class":"TypedDictType","fallback":"typing._TypedDict","items":[["id",{".class":"TypeAliasType","args":[],"type_ref":"nextcord.types.snowflake.Snowflake"}],["unavailable","builtins.bool"],["name","builtins.str"],["icon",{".class":"UnionType","items":["builtins.str",{".class":"NoneType"}]}],["splash",{".class":"UnionType","items":["builtins.str",{".class":"NoneType"}]}],["discovery_splash",{".class":"UnionType","items":["builtins.str",{".class":"NoneType"}]}],["emojis",{".class":"Instance","args":[{".class":"TypeAliasType","args":[],"type_ref":"nextcord.types.emoji.Emoji"}],"type_ref":"builtins.list"}],["features",{".class":"Instance","args":[{".class":"TypeAliasType","args":[],"type_ref":"nextcord.types.guild.GuildFeature"}],"type_ref":"builtins.list"}],["description",{".class":"UnionType","items":["builtins.str",{".class":"NoneType"}]}],["stickers",{".class":"Instance","args":[{".class":"TypeAliasType","args":[],"type_ref":"nextcord.types.sticker.GuildSticker"}],"type_ref":"builtins.list"}]],"required_keys":["description","discovery_splash","emojis","features","icon","id","name","splash","stickers"]}}},"_GuildPreviewUnique":{".class":"SymbolTableNode","kind":"Gdef","node":{".class":"TypeInfo","_promote":[],"abstract_attributes":[],"alt_promote":null,"bases":["typing._TypedDict"],"dataclass_transform_spec":null,"declared_metaclass":null,"defn":{".class":"ClassDef","fullname":"nextcord.types.guild._GuildPreviewUnique","name":"_GuildPreviewUnique","type_vars":[]},"deletable_attributes":[],"flags":[],"fullname":"nextcord.types.guild._GuildPreviewUnique","has_param_spec_type":false,"metaclass_type":null,"metadata":{},"module_name":"nextcord.types.guild","mro":["nextcord.types.guild._GuildPreviewUnique","typing._TypedDict","typing.Mapping","typing.Collection","typing.Iterable","typing.Container","builtins.object"],"names":{".class":"SymbolTable"},"self_type":null,"slots":null,"tuple_type":null,"type_vars":[],"typeddict_type":{".class":"TypedDictType","fallback":"typing._TypedDict","items":[["approximate_member_count","builtins.int"],["approximate_presence_count","builtins.int"]],"required_keys":["approximate_member_count","approximate_presence_count"]}}},"__annotations__":{".class":"SymbolTableNode","kind":"Gdef","node":{".class":"Var","flags":["is_ready"],"fullname":"nextcord.types.guild.__annotations__","name":"__annotations__","type":{".class":"Instance","args":["builtins.str",{".class":"AnyType","missing_import_name":null,"source_any":null,"type_of_any":6}],"type_ref":"builtins.dict"}}},"__doc__":{".class":"SymbolTableNode","kind":"Gdef","node":{".class":"Var","flags":["is_ready"],"fullname":"nextcord.types.guild.__doc__","name":"__doc__","type":"builtins.str"}},"__file__":{".class":"SymbolTableNode","kind":"Gdef","node":{".class":"Var","flags":["is_ready"],"fullname":"nextcord.types.guild.__file__","name":"__file__","type":"builtins.str"}},"__name__":{".class":"SymbolTableNode","kind":"Gdef","node":{".class":"Var","flags":["is_ready"],"fullname":"nextcord.types.guild.__name__","name":"__name__","type":"builtins.str"}},"__package__":{".class":"SymbolTableNode","kind":"Gdef","node":{".class":"Var","flags":["is_ready"],"fullname":"nextcord.types.guild.__package__","name":"__package__","type":"builtins.str"}}},"path":"c:\\Python312\\Lib\\site-packages\\nextcord\\types\\guild.py"}