{"id":"nextcord.audit_logs","path":"c:\\Python312\\Lib\\site-packages\\nextcord\\audit_logs.py","mtime":1709922720,"size":22538,"hash":"7845fd275f9cf12aaffcbeaeb4fd957a7b4a9908c88c89e73a1fbb965775f8ed","data_mtime":1709915491,"dependencies":["nextcord.types.audit_log","nextcord.types.auto_moderation","nextcord.types.channel","nextcord.types.role","nextcord.types.snowflake","nextcord.enums","nextcord.utils","nextcord.asset","nextcord.auto_moderation","nextcord.colour","nextcord.invite","nextcord.mixins","nextcord.object","nextcord.permissions","nextcord.abc","nextcord.emoji","nextcord.guild","nextcord.member","nextcord.role","nextcord.stage_instance","nextcord.sticker","nextcord.threads","nextcord.user","__future__","typing","nextcord","datetime","builtins","_collections_abc","_typeshed","abc","enum","nextcord.channel","nextcord.flags","nextcord.partial_emoji","nextcord.state","nextcord.types","nextcord.types.activity","nextcord.types.appinfo","nextcord.types.emoji","nextcord.types.guild","nextcord.types.invite","nextcord.types.member","nextcord.types.scheduled_events","nextcord.types.sticker","nextcord.types.threads","nextcord.types.user","nextcord.types.voice","nextcord.types.welcome_screen","types","typing_extensions"],"suppressed":[],"options":{"enable_error_code":[],"allow_redefinition":false,"always_false":[],"plugins":[],"warn_return_any":false,"enabled_error_codes":[],"disallow_untyped_defs":false,"disallow_any_explicit":false,"strict_concatenate":false,"disallow_any_generics":false,"disallow_any_unimported":false,"disallow_any_expr":false,"ignore_errors":false,"disallow_subclassing_any":false,"disallow_untyped_calls":false,"warn_no_return":true,"allow_untyped_globals":false,"local_partial_types":false,"strict_optional":true,"extra_checks":false,"disallow_any_decorated":false,"check_untyped_defs":false,"always_true":[],"disallow_untyped_decorators":false,"implicit_reexport":true,"disable_error_code":[],"platform":"win32","strict_equality":false,"follow_imports":"normal","ignore_missing_imports":false,"disabled_error_codes":[],"mypyc":false,"bazel":false,"new_type_inference":false,"disable_bytearray_promotion":false,"warn_unused_ignores":false,"follow_imports_for_stubs":false,"warn_unreachable":false,"disable_memoryview_promotion":false,"implicit_optional":false,"disallow_incomplete_defs":false},"dep_prios":[25,25,25,25,25,10,10,5,5,5,5,5,5,5,25,25,25,25,25,25,25,25,25,5,5,20,25,5,30,30,30,30,30,30,30,30,30,30,30,30,30,30,30,30,30,30,30,30,30,30,30],"dep_lines":[48,52,56,57,58,20,20,21,22,23,24,25,26,27,39,41,42,43,44,45,46,47,59,3,5,20,37,1,1,1,1,1,1,1,1,1,1,1,1,1,1,1,1,1,1,1,1,1,1,1,1],"interface_hash":"c0d267fbdc140fa3c7887a71081d7aab5ab68dcf61b0cb2a07060c20ec135ffd","version_id":"1.6.1","ignore_all":true,"plugin_data":null}