{"id":"nextcord.health_check","path":"c:\\Python312\\Lib\\site-packages\\nextcord\\health_check.py","mtime":1709922720,"size":725,"hash":"a62261ea42608dd1d8e8e8cfc633abd24dcee7f9de159f0e1b3b5f12ecc7ddce","data_mtime":1709915462,"dependencies":["warnings","builtins","_warnings","abc","typing"],"suppressed":["pkg_resources"],"options":{"enable_error_code":[],"allow_redefinition":false,"always_false":[],"plugins":[],"warn_return_any":false,"enabled_error_codes":[],"disallow_untyped_defs":false,"disallow_any_explicit":false,"strict_concatenate":false,"disallow_any_generics":false,"disallow_any_unimported":false,"disallow_any_expr":false,"ignore_errors":false,"disallow_subclassing_any":false,"disallow_untyped_calls":false,"warn_no_return":true,"allow_untyped_globals":false,"local_partial_types":false,"strict_optional":true,"extra_checks":false,"disallow_any_decorated":false,"check_untyped_defs":false,"always_true":[],"disallow_untyped_decorators":false,"implicit_reexport":true,"disable_error_code":[],"platform":"win32","strict_equality":false,"follow_imports":"normal","ignore_missing_imports":false,"disabled_error_codes":[],"mypyc":false,"bazel":false,"new_type_inference":false,"disable_bytearray_promotion":false,"warn_unused_ignores":false,"follow_imports_for_stubs":false,"warn_unreachable":false,"disable_memoryview_promotion":false,"implicit_optional":false,"disallow_incomplete_defs":false},"dep_prios":[5,5,30,30,30,5],"dep_lines":[3,1,1,1,1,5],"interface_hash":"d54feaf780173dc23068410facfe4bf93c84445404b50d2fdf8f83ba1e3b7363","version_id":"1.6.1","ignore_all":true,"plugin_data":null}