{".class":"MypyFile","_fullname":"interactions.models.internal.command","future_import_flags":["annotations"],"is_partial_stub_package":false,"is_stub":false,"names":{".class":"SymbolTable","Annotated":{".class":"SymbolTableNode","cross_ref":"typing.Annotated","kind":"Gdef","module_public":false},"Any":{".class":"SymbolTableNode","cross_ref":"typing.Any","kind":"Gdef","module_public":false},"AsyncCallable":{".class":"SymbolTableNode","cross_ref":"interactions.client.const.AsyncCallable","kind":"Gdef","module_public":false},"Awaitable":{".class":"SymbolTableNode","cross_ref":"typing.Awaitable","kind":"Gdef","module_public":false},"BaseCommand":{".class":"SymbolTableNode","kind":"Gdef","node":{".class":"TypeInfo","_promote":[],"abstract_attributes":[],"alt_promote":null,"bases":["interactions.client.mixins.serialization.DictSerializationMixin","interactions.models.internal.callback.CallbackObject"],"dataclass_transform_spec":null,"declared_metaclass":null,"defn":{".class":"ClassDef","fullname":"interactions.models.internal.command.BaseCommand","name":"BaseCommand","type_vars":[]},"deletable_attributes":[],"flags":[],"fullname":"interactions.models.internal.command.BaseCommand","has_param_spec_type":false,"metaclass_type":null,"metadata":{"attrs":{"attributes":[{"context_column":4,"context_line":14,"converter_init_type":null,"has_converter":false,"has_default":true,"init":false,"init_type":"logging.Logger","kw_only":false,"name":"logger"},{"context_column":4,"context_line":52,"converter_init_type":null,"has_converter":false,"has_default":true,"init":true,"init_type":{".class":"UnionType","items":["interactions.models.internal.extension.Extension",{".class":"NoneType"}]},"kw_only":true,"name":"extension"},{"context_column":4,"context_line":58,"converter_init_type":null,"has_converter":false,"has_default":true,"init":true,"init_type":"builtins.bool","kw_only":true,"name":"enabled"},{"context_column":4,"context_line":61,"converter_init_type":null,"has_converter":false,"has_default":true,"init":true,"init_type":{".class":"Instance","args":[{".class":"AnyType","missing_import_name":null,"source_any":null,"type_of_any":4}],"type_ref":"builtins.list"},"kw_only":true,"name":"checks"},{"context_column":4,"context_line":66,"converter_init_type":null,"has_converter":false,"has_default":true,"init":true,"init_type":"interactions.models.internal.cooldowns.Cooldown","kw_only":true,"name":"cooldown"},{"context_column":4,"context_line":71,"converter_init_type":null,"has_converter":false,"has_default":true,"init":true,"init_type":"interactions.models.internal.cooldowns.MaxConcurrency","kw_only":true,"name":"max_concurrency"},{"context_column":4,"context_line":76,"converter_init_type":null,"has_converter":false,"has_default":true,"init":true,"init_type":{".class":"CallableType","arg_kinds":[2,4],"arg_names":[null,null],"arg_types":[{".class":"AnyType","missing_import_name":null,"source_any":null,"type_of_any":2},{".class":"AnyType","missing_import_name":null,"source_any":null,"type_of_any":2}],"bound_args":[],"def_extras":{},"fallback":"builtins.function","from_concatenate":false,"implicit":false,"imprecise_arg_kinds":false,"is_ellipsis_args":true,"name":null,"ret_type":{".class":"Instance","args":[{".class":"AnyType","missing_import_name":null,"source_any":null,"type_of_any":4},{".class":"AnyType","missing_import_name":null,"source_any":null,"type_of_any":4},{".class":"AnyType","missing_import_name":null,"source_any":null,"type_of_any":4}],"type_ref":"typing.Coroutine"},"type_guard":null,"unpack_kwargs":false,"variables":[]},"kw_only":true,"name":"callback"},{"context_column":4,"context_line":81,"converter_init_type":null,"has_converter":false,"has_default":true,"init":true,"init_type":{".class":"CallableType","arg_kinds":[2,4],"arg_names":[null,null],"arg_types":[{".class":"AnyType","missing_import_name":null,"source_any":null,"type_of_any":2},{".class":"AnyType","missing_import_name":null,"source_any":null,"type_of_any":2}],"bound_args":[],"def_extras":{},"fallback":"builtins.function","from_concatenate":false,"implicit":false,"imprecise_arg_kinds":false,"is_ellipsis_args":true,"name":null,"ret_type":{".class":"Instance","args":[{".class":"AnyType","missing_import_name":null,"source_any":null,"type_of_any":4},{".class":"AnyType","missing_import_name":null,"source_any":null,"type_of_any":4},{".class":"AnyType","missing_import_name":null,"source_any":null,"type_of_any":4}],"type_ref":"typing.Coroutine"},"type_guard":null,"unpack_kwargs":false,"variables":[]},"kw_only":true,"name":"error_callback"},{"context_column":4,"context_line":86,"converter_init_type":null,"has_converter":false,"has_default":true,"init":true,"init_type":{".class":"CallableType","arg_kinds":[2,4],"arg_names":[null,null],"arg_types":[{".class":"AnyType","missing_import_name":null,"source_any":null,"type_of_any":2},{".class":"AnyType","missing_import_name":null,"source_any":null,"type_of_any":2}],"bound_args":[],"def_extras":{},"fallback":"builtins.function","from_concatenate":false,"implicit":false,"imprecise_arg_kinds":false,"is_ellipsis_args":true,"name":null,"ret_type":{".class":"Instance","args":[{".class":"AnyType","missing_import_name":null,"source_any":null,"type_of_any":4},{".class":"AnyType","missing_import_name":null,"source_any":null,"type_of_any":4},{".class":"AnyType","missing_import_name":null,"source_any":null,"type_of_any":4}],"type_ref":"typing.Coroutine"},"type_guard":null,"unpack_kwargs":false,"variables":[]},"kw_only":true,"name":"pre_run_callback"},{"context_column":4,"context_line":91,"converter_init_type":null,"has_converter":false,"has_default":true,"init":true,"init_type":{".class":"CallableType","arg_kinds":[2,4],"arg_names":[null,null],"arg_types":[{".class":"AnyType","missing_import_name":null,"source_any":null,"type_of_any":2},{".class":"AnyType","missing_import_name":null,"source_any":null,"type_of_any":2}],"bound_args":[],"def_extras":{},"fallback":"builtins.function","from_concatenate":false,"implicit":false,"imprecise_arg_kinds":false,"is_ellipsis_args":true,"name":null,"ret_type":{".class":"Instance","args":[{".class":"AnyType","missing_import_name":null,"source_any":null,"type_of_any":4},{".class":"AnyType","missing_import_name":null,"source_any":null,"type_of_any":4},{".class":"AnyType","missing_import_name":null,"source_any":null,"type_of_any":4}],"type_ref":"typing.Coroutine"},"type_guard":null,"unpack_kwargs":false,"variables":[]},"kw_only":true,"name":"post_run_callback"}],"frozen":false},"attrs_tag":{}},"module_name":"interactions.models.internal.command","mro":["interactions.models.internal.command.BaseCommand","interactions.client.mixins.serialization.DictSerializationMixin","interactions.models.internal.callback.CallbackObject","builtins.object"],"names":{".class":"SymbolTable","__attrs_attrs__":{".class":"SymbolTableNode","kind":"Mdef","node":{".class":"Var","flags":["is_classvar","is_ready","allow_incompatible_override"],"fullname":"interactions.models.internal.command.BaseCommand.__attrs_attrs__","name":"__attrs_attrs__","type":{".class":"TupleType","implicit":false,"items":[{".class":"Instance","args":["logging.Logger"],"type_ref":"attr.Attribute"},{".class":"Instance","args":[{".class":"UnionType","items":["interactions.models.internal.extension.Extension",{".class":"NoneType"}]}],"type_ref":"attr.Attribute"},{".class":"Instance","args":["builtins.bool"],"type_ref":"attr.Attribute"},{".class":"Instance","args":[{".class":"Instance","args":[{".class":"AnyType","missing_import_name":null,"source_any":null,"type_of_any":4}],"type_ref":"builtins.list"}],"type_ref":"attr.Attribute"},{".class":"Instance","args":["interactions.models.internal.cooldowns.Cooldown"],"type_ref":"attr.Attribute"},{".class":"Instance","args":["interactions.models.internal.cooldowns.MaxConcurrency"],"type_ref":"attr.Attribute"},{".class":"Instance","args":[{".class":"CallableType","arg_kinds":[2,4],"arg_names":[null,null],"arg_types":[{".class":"AnyType","missing_import_name":null,"source_any":null,"type_of_any":2},{".class":"AnyType","missing_import_name":null,"source_any":null,"type_of_any":2}],"bound_args":[],"def_extras":{},"fallback":"builtins.function","from_concatenate":false,"implicit":false,"imprecise_arg_kinds":false,"is_ellipsis_args":true,"name":null,"ret_type":{".class":"Instance","args":[{".class":"AnyType","missing_import_name":null,"source_any":null,"type_of_any":4},{".class":"AnyType","missing_import_name":null,"source_any":null,"type_of_any":4},{".class":"AnyType","missing_import_name":null,"source_any":null,"type_of_any":4}],"type_ref":"typing.Coroutine"},"type_guard":null,"unpack_kwargs":false,"variables":[]}],"type_ref":"attr.Attribute"},{".class":"Instance","args":[{".class":"CallableType","arg_kinds":[2,4],"arg_names":[null,null],"arg_types":[{".class":"AnyType","missing_import_name":null,"source_any":null,"type_of_any":2},{".class":"AnyType","missing_import_name":null,"source_any":null,"type_of_any":2}],"bound_args":[],"def_extras":{},"fallback":"builtins.function","from_concatenate":false,"implicit":false,"imprecise_arg_kinds":false,"is_ellipsis_args":true,"name":null,"ret_type":{".class":"Instance","args":[{".class":"AnyType","missing_import_name":null,"source_any":null,"type_of_any":4},{".class":"AnyType","missing_import_name":null,"source_any":null,"type_of_any":4},{".class":"AnyType","missing_import_name":null,"source_any":null,"type_of_any":4}],"type_ref":"typing.Coroutine"},"type_guard":null,"unpack_kwargs":false,"variables":[]}],"type_ref":"attr.Attribute"},{".class":"Instance","args":[{".class":"CallableType","arg_kinds":[2,4],"arg_names":[null,null],"arg_types":[{".class":"AnyType","missing_import_name":null,"source_any":null,"type_of_any":2},{".class":"AnyType","missing_import_name":null,"source_any":null,"type_of_any":2}],"bound_args":[],"def_extras":{},"fallback":"builtins.function","from_concatenate":false,"implicit":false,"imprecise_arg_kinds":false,"is_ellipsis_args":true,"name":null,"ret_type":{".class":"Instance","args":[{".class":"AnyType","missing_import_name":null,"source_any":null,"type_of_any":4},{".class":"AnyType","missing_import_name":null,"source_any":null,"type_of_any":4},{".class":"AnyType","missing_import_name":null,"source_any":null,"type_of_any":4}],"type_ref":"typing.Coroutine"},"type_guard":null,"unpack_kwargs":false,"variables":[]}],"type_ref":"attr.Attribute"},{".class":"Instance","args":[{".class":"CallableType","arg_kinds":[2,4],"arg_names":[null,null],"arg_types":[{".class":"AnyType","missing_import_name":null,"source_any":null,"type_of_any":2},{".class":"AnyType","missing_import_name":null,"source_any":null,"type_of_any":2}],"bound_args":[],"def_extras":{},"fallback":"builtins.function","from_concatenate":false,"implicit":false,"imprecise_arg_kinds":false,"is_ellipsis_args":true,"name":null,"ret_type":{".class":"Instance","args":[{".class":"AnyType","missing_import_name":null,"source_any":null,"type_of_any":4},{".class":"AnyType","missing_import_name":null,"source_any":null,"type_of_any":4},{".class":"AnyType","missing_import_name":null,"source_any":null,"type_of_any":4}],"type_ref":"typing.Coroutine"},"type_guard":null,"unpack_kwargs":false,"variables":[]}],"type_ref":"attr.Attribute"}],"partial_fallback":"interactions.models.internal.command.BaseCommand.__interactions_models_internal_command_BaseCommand_AttrsAttributes__"}},"plugin_generated":true},"__attrs_post_init__":{".class":"SymbolTableNode","kind":"Mdef","node":{".class":"FuncDef","abstract_status":0,"arg_kinds":[0],"arg_names":["self"],"dataclass_transform_spec":null,"flags":[],"fullname":"interactions.models.internal.command.BaseCommand.__attrs_post_init__","name":"__attrs_post_init__","type":{".class":"CallableType","arg_kinds":[0],"arg_names":["self"],"arg_types":["interactions.models.internal.command.BaseCommand"],"bound_args":[],"def_extras":{"first_arg":"self"},"fallback":"builtins.function","from_concatenate":false,"implicit":false,"imprecise_arg_kinds":false,"is_ellipsis_args":false,"name":"__attrs_post_init__ of BaseCommand","ret_type":{".class":"NoneType"},"type_guard":null,"unpack_kwargs":false,"variables":[]}}},"__call__":{".class":"SymbolTableNode","kind":"Mdef","node":{".class":"FuncDef","abstract_status":0,"arg_kinds":[0,0,2,4],"arg_names":["self","context","args","kwargs"],"dataclass_transform_spec":null,"flags":["is_coroutine"],"fullname":"interactions.models.internal.command.BaseCommand.__call__","name":"__call__","type":{".class":"CallableType","arg_kinds":[0,0,2,4],"arg_names":["self","context","args","kwargs"],"arg_types":["interactions.models.internal.command.BaseCommand","interactions.models.internal.context.BaseContext",{".class":"AnyType","missing_import_name":null,"source_any":null,"type_of_any":1},{".class":"AnyType","missing_import_name":null,"source_any":null,"type_of_any":1}],"bound_args":[],"def_extras":{"first_arg":"self"},"fallback":"builtins.function","from_concatenate":false,"implicit":false,"imprecise_arg_kinds":false,"is_ellipsis_args":false,"name":"__call__ of BaseCommand","ret_type":{".class":"Instance","args":[{".class":"AnyType","missing_import_name":null,"source_any":null,"type_of_any":6},{".class":"AnyType","missing_import_name":null,"source_any":null,"type_of_any":6},{".class":"NoneType"}],"type_ref":"typing.Coroutine"},"type_guard":null,"unpack_kwargs":false,"variables":[]}}},"__hash__":{".class":"SymbolTableNode","kind":"Mdef","node":{".class":"FuncDef","abstract_status":0,"arg_kinds":[0],"arg_names":["self"],"dataclass_transform_spec":null,"flags":[],"fullname":"interactions.models.internal.command.BaseCommand.__hash__","name":"__hash__","type":{".class":"CallableType","arg_kinds":[0],"arg_names":["self"],"arg_types":["interactions.models.internal.command.BaseCommand"],"bound_args":[],"def_extras":{"first_arg":"self"},"fallback":"builtins.function","from_concatenate":false,"implicit":false,"imprecise_arg_kinds":false,"is_ellipsis_args":false,"name":"__hash__ of BaseCommand","ret_type":"builtins.int","type_guard":null,"unpack_kwargs":false,"variables":[]}}},"__init__":{".class":"SymbolTableNode","kind":"Mdef","node":{".class":"FuncDef","abstract_status":0,"arg_kinds":[0,5,5,5,5,5,5,5,5,5],"arg_names":["self","extension","enabled","checks","cooldown","max_concurrency","callback","error_callback","pre_run_callback","post_run_callback"],"dataclass_transform_spec":null,"flags":[],"fullname":"interactions.models.internal.command.BaseCommand.__init__","name":"__init__","type":{".class":"CallableType","arg_kinds":[0,5,5,5,5,5,5,5,5,5],"arg_names":["self","extension","enabled","checks","cooldown","max_concurrency","callback","error_callback","pre_run_callback","post_run_callback"],"arg_types":["interactions.models.internal.command.BaseCommand",{".class":"UnionType","items":["interactions.models.internal.extension.Extension",{".class":"NoneType"}]},"builtins.bool",{".class":"Instance","args":[{".class":"AnyType","missing_import_name":null,"source_any":null,"type_of_any":4}],"type_ref":"builtins.list"},"interactions.models.internal.cooldowns.Cooldown","interactions.models.internal.cooldowns.MaxConcurrency",{".class":"CallableType","arg_kinds":[2,4],"arg_names":[null,null],"arg_types":[{".class":"AnyType","missing_import_name":null,"source_any":null,"type_of_any":2},{".class":"AnyType","missing_import_name":null,"source_any":null,"type_of_any":2}],"bound_args":[],"def_extras":{},"fallback":"builtins.function","from_concatenate":false,"implicit":false,"imprecise_arg_kinds":false,"is_ellipsis_args":true,"name":null,"ret_type":{".class":"Instance","args":[{".class":"AnyType","missing_import_name":null,"source_any":null,"type_of_any":4},{".class":"AnyType","missing_import_name":null,"source_any":null,"type_of_any":4},{".class":"AnyType","missing_import_name":null,"source_any":null,"type_of_any":4}],"type_ref":"typing.Coroutine"},"type_guard":null,"unpack_kwargs":false,"variables":[]},{".class":"CallableType","arg_kinds":[2,4],"arg_names":[null,null],"arg_types":[{".class":"AnyType","missing_import_name":null,"source_any":null,"type_of_any":2},{".class":"AnyType","missing_import_name":null,"source_any":null,"type_of_any":2}],"bound_args":[],"def_extras":{},"fallback":"builtins.function","from_concatenate":false,"implicit":false,"imprecise_arg_kinds":false,"is_ellipsis_args":true,"name":null,"ret_type":{".class":"Instance","args":[{".class":"AnyType","missing_import_name":null,"source_any":null,"type_of_any":4},{".class":"AnyType","missing_import_name":null,"source_any":null,"type_of_any":4},{".class":"AnyType","missing_import_name":null,"source_any":null,"type_of_any":4}],"type_ref":"typing.Coroutine"},"type_guard":null,"unpack_kwargs":false,"variables":[]},{".class":"CallableType","arg_kinds":[2,4],"arg_names":[null,null],"arg_types":[{".class":"AnyType","missing_import_name":null,"source_any":null,"type_of_any":2},{".class":"AnyType","missing_import_name":null,"source_any":null,"type_of_any":2}],"bound_args":[],"def_extras":{},"fallback":"builtins.function","from_concatenate":false,"implicit":false,"imprecise_arg_kinds":false,"is_ellipsis_args":true,"name":null,"ret_type":{".class":"Instance","args":[{".class":"AnyType","missing_import_name":null,"source_any":null,"type_of_any":4},{".class":"AnyType","missing_import_name":null,"source_any":null,"type_of_any":4},{".class":"AnyType","missing_import_name":null,"source_any":null,"type_of_any":4}],"type_ref":"typing.Coroutine"},"type_guard":null,"unpack_kwargs":false,"variables":[]},{".class":"CallableType","arg_kinds":[2,4],"arg_names":[null,null],"arg_types":[{".class":"AnyType","missing_import_name":null,"source_any":null,"type_of_any":2},{".class":"AnyType","missing_import_name":null,"source_any":null,"type_of_any":2}],"bound_args":[],"def_extras":{},"fallback":"builtins.function","from_concatenate":false,"implicit":false,"imprecise_arg_kinds":false,"is_ellipsis_args":true,"name":null,"ret_type":{".class":"Instance","args":[{".class":"AnyType","missing_import_name":null,"source_any":null,"type_of_any":4},{".class":"AnyType","missing_import_name":null,"source_any":null,"type_of_any":4},{".class":"AnyType","missing_import_name":null,"source_any":null,"type_of_any":4}],"type_ref":"typing.Coroutine"},"type_guard":null,"unpack_kwargs":false,"variables":[]}],"bound_args":[],"def_extras":{},"fallback":"builtins.function","from_concatenate":false,"implicit":false,"imprecise_arg_kinds":false,"is_ellipsis_args":false,"name":"__init__ of BaseCommand","ret_type":{".class":"NoneType"},"type_guard":null,"unpack_kwargs":false,"variables":[]}},"plugin_generated":true},"__interactions_models_internal_command_BaseCommand_AttrsAttributes__":{".class":"SymbolTableNode","kind":"Mdef","node":{".class":"TypeInfo","_promote":[],"abstract_attributes":[],"alt_promote":null,"bases":[{".class":"Instance","args":[{".class":"Instance","args":[{".class":"AnyType","missing_import_name":null,"source_any":null,"type_of_any":2}],"type_ref":"attr.Attribute"}],"type_ref":"builtins.tuple"}],"dataclass_transform_spec":null,"declared_metaclass":null,"defn":{".class":"ClassDef","fullname":"interactions.models.internal.command.BaseCommand.__interactions_models_internal_command_BaseCommand_AttrsAttributes__","name":"__interactions_models_internal_command_BaseCommand_AttrsAttributes__","type_vars":[]},"deletable_attributes":[],"flags":[],"fullname":"interactions.models.internal.command.BaseCommand.__interactions_models_internal_command_BaseCommand_AttrsAttributes__","has_param_spec_type":false,"metaclass_type":null,"metadata":{},"module_name":"interactions.models.internal.command","mro":["interactions.models.internal.command.BaseCommand.__interactions_models_internal_command_BaseCommand_AttrsAttributes__","builtins.tuple","typing.Sequence","typing.Collection","typing.Reversible","typing.Iterable","typing.Container","builtins.object"],"names":{".class":"SymbolTable","callback":{".class":"SymbolTableNode","kind":"Mdef","node":{".class":"Var","flags":["is_property","is_ready"],"fullname":"callback","name":"callback","type":{".class":"Instance","args":[{".class":"CallableType","arg_kinds":[2,4],"arg_names":[null,null],"arg_types":[{".class":"AnyType","missing_import_name":null,"source_any":null,"type_of_any":2},{".class":"AnyType","missing_import_name":null,"source_any":null,"type_of_any":2}],"bound_args":[],"def_extras":{},"fallback":"builtins.function","from_concatenate":false,"implicit":false,"imprecise_arg_kinds":false,"is_ellipsis_args":true,"name":null,"ret_type":{".class":"Instance","args":[{".class":"AnyType","missing_import_name":null,"source_any":null,"type_of_any":4},{".class":"AnyType","missing_import_name":null,"source_any":null,"type_of_any":4},{".class":"AnyType","missing_import_name":null,"source_any":null,"type_of_any":4}],"type_ref":"typing.Coroutine"},"type_guard":null,"unpack_kwargs":false,"variables":[]}],"type_ref":"attr.Attribute"}},"plugin_generated":true},"checks":{".class":"SymbolTableNode","kind":"Mdef","node":{".class":"Var","flags":["is_property","is_ready"],"fullname":"checks","name":"checks","type":{".class":"Instance","args":[{".class":"Instance","args":[{".class":"AnyType","missing_import_name":null,"source_any":null,"type_of_any":4}],"type_ref":"builtins.list"}],"type_ref":"attr.Attribute"}},"plugin_generated":true},"cooldown":{".class":"SymbolTableNode","kind":"Mdef","node":{".class":"Var","flags":["is_property","is_ready"],"fullname":"cooldown","name":"cooldown","type":{".class":"Instance","args":["interactions.models.internal.cooldowns.Cooldown"],"type_ref":"attr.Attribute"}},"plugin_generated":true},"enabled":{".class":"SymbolTableNode","kind":"Mdef","node":{".class":"Var","flags":["is_property","is_ready"],"fullname":"enabled","name":"enabled","type":{".class":"Instance","args":["builtins.bool"],"type_ref":"attr.Attribute"}},"plugin_generated":true},"error_callback":{".class":"SymbolTableNode","kind":"Mdef","node":{".class":"Var","flags":["is_property","is_ready"],"fullname":"error_callback","name":"error_callback","type":{".class":"Instance","args":[{".class":"CallableType","arg_kinds":[2,4],"arg_names":[null,null],"arg_types":[{".class":"AnyType","missing_import_name":null,"source_any":null,"type_of_any":2},{".class":"AnyType","missing_import_name":null,"source_any":null,"type_of_any":2}],"bound_args":[],"def_extras":{},"fallback":"builtins.function","from_concatenate":false,"implicit":false,"imprecise_arg_kinds":false,"is_ellipsis_args":true,"name":null,"ret_type":{".class":"Instance","args":[{".class":"AnyType","missing_import_name":null,"source_any":null,"type_of_any":4},{".class":"AnyType","missing_import_name":null,"source_any":null,"type_of_any":4},{".class":"AnyType","missing_import_name":null,"source_any":null,"type_of_any":4}],"type_ref":"typing.Coroutine"},"type_guard":null,"unpack_kwargs":false,"variables":[]}],"type_ref":"attr.Attribute"}},"plugin_generated":true},"extension":{".class":"SymbolTableNode","kind":"Mdef","node":{".class":"Var","flags":["is_property","is_ready"],"fullname":"extension","name":"extension","type":{".class":"Instance","args":[{".class":"UnionType","items":["interactions.models.internal.extension.Extension",{".class":"NoneType"}]}],"type_ref":"attr.Attribute"}},"plugin_generated":true},"logger":{".class":"SymbolTableNode","kind":"Mdef","node":{".class":"Var","flags":["is_property","is_ready"],"fullname":"logger","name":"logger","type":{".class":"Instance","args":["logging.Logger"],"type_ref":"attr.Attribute"}},"plugin_generated":true},"max_concurrency":{".class":"SymbolTableNode","kind":"Mdef","node":{".class":"Var","flags":["is_property","is_ready"],"fullname":"max_concurrency","name":"max_concurrency","type":{".class":"Instance","args":["interactions.models.internal.cooldowns.MaxConcurrency"],"type_ref":"attr.Attribute"}},"plugin_generated":true},"post_run_callback":{".class":"SymbolTableNode","kind":"Mdef","node":{".class":"Var","flags":["is_property","is_ready"],"fullname":"post_run_callback","name":"post_run_callback","type":{".class":"Instance","args":[{".class":"CallableType","arg_kinds":[2,4],"arg_names":[null,null],"arg_types":[{".class":"AnyType","missing_import_name":null,"source_any":null,"type_of_any":2},{".class":"AnyType","missing_import_name":null,"source_any":null,"type_of_any":2}],"bound_args":[],"def_extras":{},"fallback":"builtins.function","from_concatenate":false,"implicit":false,"imprecise_arg_kinds":false,"is_ellipsis_args":true,"name":null,"ret_type":{".class":"Instance","args":[{".class":"AnyType","missing_import_name":null,"source_any":null,"type_of_any":4},{".class":"AnyType","missing_import_name":null,"source_any":null,"type_of_any":4},{".class":"AnyType","missing_import_name":null,"source_any":null,"type_of_any":4}],"type_ref":"typing.Coroutine"},"type_guard":null,"unpack_kwargs":false,"variables":[]}],"type_ref":"attr.Attribute"}},"plugin_generated":true},"pre_run_callback":{".class":"SymbolTableNode","kind":"Mdef","node":{".class":"Var","flags":["is_property","is_ready"],"fullname":"pre_run_callback","name":"pre_run_callback","type":{".class":"Instance","args":[{".class":"CallableType","arg_kinds":[2,4],"arg_names":[null,null],"arg_types":[{".class":"AnyType","missing_import_name":null,"source_any":null,"type_of_any":2},{".class":"AnyType","missing_import_name":null,"source_any":null,"type_of_any":2}],"bound_args":[],"def_extras":{},"fallback":"builtins.function","from_concatenate":false,"implicit":false,"imprecise_arg_kinds":false,"is_ellipsis_args":true,"name":null,"ret_type":{".class":"Instance","args":[{".class":"AnyType","missing_import_name":null,"source_any":null,"type_of_any":4},{".class":"AnyType","missing_import_name":null,"source_any":null,"type_of_any":4},{".class":"AnyType","missing_import_name":null,"source_any":null,"type_of_any":4}],"type_ref":"typing.Coroutine"},"type_guard":null,"unpack_kwargs":false,"variables":[]}],"type_ref":"attr.Attribute"}},"plugin_generated":true}},"self_type":null,"slots":null,"tuple_type":null,"type_vars":[],"typeddict_type":null},"plugin_generated":true},"__match_args__":{".class":"SymbolTableNode","kind":"Mdef","node":{".class":"Var","flags":["is_ready","allow_incompatible_override"],"fullname":"interactions.models.internal.command.BaseCommand.__match_args__","name":"__match_args__","type":{".class":"TupleType","implicit":false,"items":[],"partial_fallback":{".class":"Instance","args":[{".class":"AnyType","missing_import_name":null,"source_any":null,"type_of_any":6}],"type_ref":"builtins.tuple"}}},"plugin_generated":true},"__slots__":{".class":"SymbolTableNode","kind":"Mdef","node":{".class":"Var","flags":["is_ready","allow_incompatible_override"],"fullname":"interactions.models.internal.command.BaseCommand.__slots__","name":"__slots__","type":{".class":"TupleType","implicit":false,"items":["builtins.str","builtins.str","builtins.str","builtins.str","builtins.str","builtins.str","builtins.str","builtins.str","builtins.str","builtins.str"],"partial_fallback":{".class":"Instance","args":[{".class":"AnyType","missing_import_name":null,"source_any":null,"type_of_any":6}],"type_ref":"builtins.tuple"}}},"plugin_generated":true},"_can_run":{".class":"SymbolTableNode","kind":"Mdef","node":{".class":"FuncDef","abstract_status":0,"arg_kinds":[0,0],"arg_names":["self","context"],"dataclass_transform_spec":null,"flags":["is_coroutine"],"fullname":"interactions.models.internal.command.BaseCommand._can_run","name":"_can_run","type":{".class":"CallableType","arg_kinds":[0,0],"arg_names":["self","context"],"arg_types":["interactions.models.internal.command.BaseCommand","interactions.models.internal.context.BaseContext"],"bound_args":[],"def_extras":{"first_arg":"self"},"fallback":"builtins.function","from_concatenate":false,"implicit":false,"imprecise_arg_kinds":false,"is_ellipsis_args":false,"name":"_can_run of BaseCommand","ret_type":{".class":"Instance","args":[{".class":"AnyType","missing_import_name":null,"source_any":null,"type_of_any":6},{".class":"AnyType","missing_import_name":null,"source_any":null,"type_of_any":6},"builtins.bool"],"type_ref":"typing.Coroutine"},"type_guard":null,"unpack_kwargs":false,"variables":[]}}},"_get_converter_function":{".class":"SymbolTableNode","kind":"Mdef","node":{".class":"Decorator","func":{".class":"FuncDef","abstract_status":0,"arg_kinds":[0,0],"arg_names":["anno","name"],"dataclass_transform_spec":null,"flags":["is_static","is_decorated"],"fullname":"interactions.models.internal.command.BaseCommand._get_converter_function","name":"_get_converter_function","type":{".class":"CallableType","arg_kinds":[0,0],"arg_names":["anno","name"],"arg_types":[{".class":"UnionType","items":[{".class":"TypeType","item":{".class":"Instance","args":[{".class":"AnyType","missing_import_name":null,"source_any":null,"type_of_any":4}],"type_ref":"interactions.models.internal.protocols.Converter"}},{".class":"Instance","args":[{".class":"AnyType","missing_import_name":null,"source_any":null,"type_of_any":4}],"type_ref":"interactions.models.internal.protocols.Converter"}]},"builtins.str"],"bound_args":[],"def_extras":{"first_arg":null},"fallback":"builtins.function","from_concatenate":false,"implicit":false,"imprecise_arg_kinds":false,"is_ellipsis_args":false,"name":"_get_converter_function of BaseCommand","ret_type":{".class":"CallableType","arg_kinds":[0,0],"arg_names":[null,null],"arg_types":["interactions.models.internal.context.BaseContext","builtins.str"],"bound_args":[],"def_extras":{},"fallback":"builtins.function","from_concatenate":false,"implicit":false,"imprecise_arg_kinds":false,"is_ellipsis_args":false,"name":null,"ret_type":{".class":"AnyType","missing_import_name":null,"source_any":null,"type_of_any":2},"type_guard":null,"unpack_kwargs":false,"variables":[]},"type_guard":null,"unpack_kwargs":false,"variables":[]}},"is_overload":false,"var":{".class":"Var","flags":["is_initialized_in_class","is_staticmethod","is_ready","is_inferred"],"fullname":"interactions.models.internal.command.BaseCommand._get_converter_function","name":"_get_converter_function","type":{".class":"CallableType","arg_kinds":[0,0],"arg_names":["anno","name"],"arg_types":[{".class":"UnionType","items":[{".class":"TypeType","item":{".class":"Instance","args":[{".class":"AnyType","missing_import_name":null,"source_any":null,"type_of_any":4}],"type_ref":"interactions.models.internal.protocols.Converter"}},{".class":"Instance","args":[{".class":"AnyType","missing_import_name":null,"source_any":null,"type_of_any":4}],"type_ref":"interactions.models.internal.protocols.Converter"}]},"builtins.str"],"bound_args":[],"def_extras":{"first_arg":null},"fallback":"builtins.function","from_concatenate":false,"implicit":false,"imprecise_arg_kinds":false,"is_ellipsis_args":false,"name":"_get_converter_function of BaseCommand","ret_type":{".class":"CallableType","arg_kinds":[0,0],"arg_names":[null,null],"arg_types":["interactions.models.internal.context.BaseContext","builtins.str"],"bound_args":[],"def_extras":{},"fallback":"builtins.function","from_concatenate":false,"implicit":false,"imprecise_arg_kinds":false,"is_ellipsis_args":false,"name":null,"ret_type":{".class":"AnyType","missing_import_name":null,"source_any":null,"type_of_any":2},"type_guard":null,"unpack_kwargs":false,"variables":[]},"type_guard":null,"unpack_kwargs":false,"variables":[]}}}},"add_check":{".class":"SymbolTableNode","kind":"Mdef","node":{".class":"FuncDef","abstract_status":0,"arg_kinds":[0,0],"arg_names":["self","check"],"dataclass_transform_spec":null,"flags":[],"fullname":"interactions.models.internal.command.BaseCommand.add_check","name":"add_check","type":{".class":"CallableType","arg_kinds":[0,0],"arg_names":["self","check"],"arg_types":["interactions.models.internal.command.BaseCommand",{".class":"CallableType","arg_kinds":[2,4],"arg_names":[null,null],"arg_types":[{".class":"AnyType","missing_import_name":null,"source_any":null,"type_of_any":2},{".class":"AnyType","missing_import_name":null,"source_any":null,"type_of_any":2}],"bound_args":[],"def_extras":{},"fallback":"builtins.function","from_concatenate":false,"implicit":false,"imprecise_arg_kinds":false,"is_ellipsis_args":true,"name":null,"ret_type":{".class":"Instance","args":["builtins.bool"],"type_ref":"typing.Awaitable"},"type_guard":null,"unpack_kwargs":false,"variables":[]}],"bound_args":[],"def_extras":{"first_arg":"self"},"fallback":"builtins.function","from_concatenate":false,"implicit":false,"imprecise_arg_kinds":false,"is_ellipsis_args":false,"name":"add_check of BaseCommand","ret_type":{".class":"NoneType"},"type_guard":null,"unpack_kwargs":false,"variables":[]}}},"call_callback":{".class":"SymbolTableNode","kind":"Mdef","node":{".class":"FuncDef","abstract_status":0,"arg_kinds":[0,0,0],"arg_names":["self","callback","context"],"dataclass_transform_spec":null,"flags":["is_coroutine"],"fullname":"interactions.models.internal.command.BaseCommand.call_callback","name":"call_callback","type":{".class":"CallableType","arg_kinds":[0,0,0],"arg_names":["self","callback","context"],"arg_types":["interactions.models.internal.command.BaseCommand",{".class":"CallableType","arg_kinds":[2,4],"arg_names":[null,null],"arg_types":[{".class":"AnyType","missing_import_name":null,"source_any":null,"type_of_any":4},{".class":"AnyType","missing_import_name":null,"source_any":null,"type_of_any":4}],"bound_args":[],"def_extras":{},"fallback":"builtins.function","from_concatenate":false,"implicit":false,"imprecise_arg_kinds":false,"is_ellipsis_args":true,"name":null,"ret_type":{".class":"AnyType","missing_import_name":null,"source_any":null,"type_of_any":4},"type_guard":null,"unpack_kwargs":false,"variables":[]},"interactions.models.internal.context.BaseContext"],"bound_args":[],"def_extras":{"first_arg":"self"},"fallback":"builtins.function","from_concatenate":false,"implicit":false,"imprecise_arg_kinds":false,"is_ellipsis_args":false,"name":"call_callback of BaseCommand","ret_type":{".class":"Instance","args":[{".class":"AnyType","missing_import_name":null,"source_any":null,"type_of_any":6},{".class":"AnyType","missing_import_name":null,"source_any":null,"type_of_any":6},{".class":"NoneType"}],"type_ref":"typing.Coroutine"},"type_guard":null,"unpack_kwargs":false,"variables":[]}}},"callback":{".class":"SymbolTableNode","kind":"Mdef","node":{".class":"Var","flags":["is_ready","has_explicit_value"],"fullname":"interactions.models.internal.command.BaseCommand.callback","name":"callback","type":{".class":"CallableType","arg_kinds":[2,4],"arg_names":[null,null],"arg_types":[{".class":"AnyType","missing_import_name":null,"source_any":null,"type_of_any":2},{".class":"AnyType","missing_import_name":null,"source_any":null,"type_of_any":2}],"bound_args":[],"def_extras":{},"fallback":"builtins.function","from_concatenate":false,"implicit":false,"imprecise_arg_kinds":false,"is_ellipsis_args":true,"name":null,"ret_type":{".class":"Instance","args":[{".class":"AnyType","missing_import_name":null,"source_any":null,"type_of_any":4},{".class":"AnyType","missing_import_name":null,"source_any":null,"type_of_any":4},{".class":"AnyType","missing_import_name":null,"source_any":null,"type_of_any":4}],"type_ref":"typing.Coroutine"},"type_guard":null,"unpack_kwargs":false,"variables":[]}}},"checks":{".class":"SymbolTableNode","kind":"Mdef","node":{".class":"Var","flags":["is_ready","has_explicit_value"],"fullname":"interactions.models.internal.command.BaseCommand.checks","name":"checks","type":{".class":"Instance","args":[{".class":"AnyType","missing_import_name":null,"source_any":null,"type_of_any":4}],"type_ref":"builtins.list"}}},"cooldown":{".class":"SymbolTableNode","kind":"Mdef","node":{".class":"Var","flags":["is_ready","has_explicit_value"],"fullname":"interactions.models.internal.command.BaseCommand.cooldown","name":"cooldown","type":"interactions.models.internal.cooldowns.Cooldown"}},"enabled":{".class":"SymbolTableNode","kind":"Mdef","node":{".class":"Var","flags":["is_ready","has_explicit_value"],"fullname":"interactions.models.internal.command.BaseCommand.enabled","name":"enabled","type":"builtins.bool"}},"error":{".class":"SymbolTableNode","kind":"Mdef","node":{".class":"FuncDef","abstract_status":0,"arg_kinds":[0,0],"arg_names":["self","call"],"dataclass_transform_spec":null,"flags":[],"fullname":"interactions.models.internal.command.BaseCommand.error","name":"error","type":{".class":"CallableType","arg_kinds":[0,0],"arg_names":["self","call"],"arg_types":["interactions.models.internal.command.BaseCommand",{".class":"CallableType","arg_kinds":[2,4],"arg_names":[null,null],"arg_types":[{".class":"AnyType","missing_import_name":null,"source_any":null,"type_of_any":2},{".class":"AnyType","missing_import_name":null,"source_any":null,"type_of_any":2}],"bound_args":[],"def_extras":{},"fallback":"builtins.function","from_concatenate":false,"implicit":false,"imprecise_arg_kinds":false,"is_ellipsis_args":true,"name":null,"ret_type":{".class":"Instance","args":[{".class":"AnyType","missing_import_name":null,"source_any":null,"type_of_any":4},{".class":"AnyType","missing_import_name":null,"source_any":null,"type_of_any":4},{".class":"AnyType","missing_import_name":null,"source_any":null,"type_of_any":4}],"type_ref":"typing.Coroutine"},"type_guard":null,"unpack_kwargs":false,"variables":[]}],"bound_args":[],"def_extras":{"first_arg":"self"},"fallback":"builtins.function","from_concatenate":false,"implicit":false,"imprecise_arg_kinds":false,"is_ellipsis_args":false,"name":"error of BaseCommand","ret_type":{".class":"CallableType","arg_kinds":[2,4],"arg_names":[null,null],"arg_types":[{".class":"AnyType","missing_import_name":null,"source_any":null,"type_of_any":2},{".class":"AnyType","missing_import_name":null,"source_any":null,"type_of_any":2}],"bound_args":[],"def_extras":{},"fallback":"builtins.function","from_concatenate":false,"implicit":false,"imprecise_arg_kinds":false,"is_ellipsis_args":true,"name":null,"ret_type":{".class":"Instance","args":[{".class":"AnyType","missing_import_name":null,"source_any":null,"type_of_any":4},{".class":"AnyType","missing_import_name":null,"source_any":null,"type_of_any":4},{".class":"AnyType","missing_import_name":null,"source_any":null,"type_of_any":4}],"type_ref":"typing.Coroutine"},"type_guard":null,"unpack_kwargs":false,"variables":[]},"type_guard":null,"unpack_kwargs":false,"variables":[]}}},"error_callback":{".class":"SymbolTableNode","kind":"Mdef","node":{".class":"Var","flags":["is_ready","has_explicit_value"],"fullname":"interactions.models.internal.command.BaseCommand.error_callback","name":"error_callback","type":{".class":"CallableType","arg_kinds":[2,4],"arg_names":[null,null],"arg_types":[{".class":"AnyType","missing_import_name":null,"source_any":null,"type_of_any":2},{".class":"AnyType","missing_import_name":null,"source_any":null,"type_of_any":2}],"bound_args":[],"def_extras":{},"fallback":"builtins.function","from_concatenate":false,"implicit":false,"imprecise_arg_kinds":false,"is_ellipsis_args":true,"name":null,"ret_type":{".class":"Instance","args":[{".class":"AnyType","missing_import_name":null,"source_any":null,"type_of_any":4},{".class":"AnyType","missing_import_name":null,"source_any":null,"type_of_any":4},{".class":"AnyType","missing_import_name":null,"source_any":null,"type_of_any":4}],"type_ref":"typing.Coroutine"},"type_guard":null,"unpack_kwargs":false,"variables":[]}}},"extension":{".class":"SymbolTableNode","kind":"Mdef","node":{".class":"Var","flags":["is_ready","has_explicit_value"],"fullname":"interactions.models.internal.command.BaseCommand.extension","name":"extension","type":{".class":"UnionType","items":["interactions.models.internal.extension.Extension",{".class":"NoneType"}]}}},"max_concurrency":{".class":"SymbolTableNode","kind":"Mdef","node":{".class":"Var","flags":["is_ready","has_explicit_value"],"fullname":"interactions.models.internal.command.BaseCommand.max_concurrency","name":"max_concurrency","type":"interactions.models.internal.cooldowns.MaxConcurrency"}},"param_config":{".class":"SymbolTableNode","kind":"Mdef","node":{".class":"FuncDef","abstract_status":0,"arg_kinds":[0,0,0],"arg_names":["self","annotation","name"],"dataclass_transform_spec":null,"flags":[],"fullname":"interactions.models.internal.command.BaseCommand.param_config","name":"param_config","type":{".class":"CallableType","arg_kinds":[0,0,0],"arg_names":["self","annotation","name"],"arg_types":["interactions.models.internal.command.BaseCommand",{".class":"AnyType","missing_import_name":null,"source_any":null,"type_of_any":2},"builtins.str"],"bound_args":[],"def_extras":{"first_arg":"self"},"fallback":"builtins.function","from_concatenate":false,"implicit":false,"imprecise_arg_kinds":false,"is_ellipsis_args":false,"name":"param_config of BaseCommand","ret_type":{".class":"TupleType","implicit":false,"items":[{".class":"CallableType","arg_kinds":[2,4],"arg_names":[null,null],"arg_types":[{".class":"AnyType","missing_import_name":null,"source_any":null,"type_of_any":4},{".class":"AnyType","missing_import_name":null,"source_any":null,"type_of_any":4}],"bound_args":[],"def_extras":{},"fallback":"builtins.function","from_concatenate":false,"implicit":false,"imprecise_arg_kinds":false,"is_ellipsis_args":true,"name":null,"ret_type":{".class":"AnyType","missing_import_name":null,"source_any":null,"type_of_any":4},"type_guard":null,"unpack_kwargs":false,"variables":[]},{".class":"UnionType","items":[{".class":"Instance","args":[{".class":"AnyType","missing_import_name":null,"source_any":null,"type_of_any":4},{".class":"AnyType","missing_import_name":null,"source_any":null,"type_of_any":4}],"type_ref":"builtins.dict"},{".class":"NoneType"}]}],"partial_fallback":{".class":"Instance","args":[{".class":"AnyType","missing_import_name":null,"source_any":null,"type_of_any":6}],"type_ref":"builtins.tuple"}},"type_guard":null,"unpack_kwargs":false,"variables":[]}}},"post_run":{".class":"SymbolTableNode","kind":"Mdef","node":{".class":"FuncDef","abstract_status":0,"arg_kinds":[0,0],"arg_names":["self","call"],"dataclass_transform_spec":null,"flags":[],"fullname":"interactions.models.internal.command.BaseCommand.post_run","name":"post_run","type":{".class":"CallableType","arg_kinds":[0,0],"arg_names":["self","call"],"arg_types":["interactions.models.internal.command.BaseCommand",{".class":"CallableType","arg_kinds":[2,4],"arg_names":[null,null],"arg_types":[{".class":"AnyType","missing_import_name":null,"source_any":null,"type_of_any":2},{".class":"AnyType","missing_import_name":null,"source_any":null,"type_of_any":2}],"bound_args":[],"def_extras":{},"fallback":"builtins.function","from_concatenate":false,"implicit":false,"imprecise_arg_kinds":false,"is_ellipsis_args":true,"name":null,"ret_type":{".class":"Instance","args":[{".class":"AnyType","missing_import_name":null,"source_any":null,"type_of_any":4},{".class":"AnyType","missing_import_name":null,"source_any":null,"type_of_any":4},{".class":"AnyType","missing_import_name":null,"source_any":null,"type_of_any":4}],"type_ref":"typing.Coroutine"},"type_guard":null,"unpack_kwargs":false,"variables":[]}],"bound_args":[],"def_extras":{"first_arg":"self"},"fallback":"builtins.function","from_concatenate":false,"implicit":false,"imprecise_arg_kinds":false,"is_ellipsis_args":false,"name":"post_run of BaseCommand","ret_type":{".class":"CallableType","arg_kinds":[2,4],"arg_names":[null,null],"arg_types":[{".class":"AnyType","missing_import_name":null,"source_any":null,"type_of_any":2},{".class":"AnyType","missing_import_name":null,"source_any":null,"type_of_any":2}],"bound_args":[],"def_extras":{},"fallback":"builtins.function","from_concatenate":false,"implicit":false,"imprecise_arg_kinds":false,"is_ellipsis_args":true,"name":null,"ret_type":{".class":"Instance","args":[{".class":"AnyType","missing_import_name":null,"source_any":null,"type_of_any":4},{".class":"AnyType","missing_import_name":null,"source_any":null,"type_of_any":4},{".class":"AnyType","missing_import_name":null,"source_any":null,"type_of_any":4}],"type_ref":"typing.Coroutine"},"type_guard":null,"unpack_kwargs":false,"variables":[]},"type_guard":null,"unpack_kwargs":false,"variables":[]}}},"post_run_callback":{".class":"SymbolTableNode","kind":"Mdef","node":{".class":"Var","flags":["is_ready","has_explicit_value"],"fullname":"interactions.models.internal.command.BaseCommand.post_run_callback","name":"post_run_callback","type":{".class":"CallableType","arg_kinds":[2,4],"arg_names":[null,null],"arg_types":[{".class":"AnyType","missing_import_name":null,"source_any":null,"type_of_any":2},{".class":"AnyType","missing_import_name":null,"source_any":null,"type_of_any":2}],"bound_args":[],"def_extras":{},"fallback":"builtins.function","from_concatenate":false,"implicit":false,"imprecise_arg_kinds":false,"is_ellipsis_args":true,"name":null,"ret_type":{".class":"Instance","args":[{".class":"AnyType","missing_import_name":null,"source_any":null,"type_of_any":4},{".class":"AnyType","missing_import_name":null,"source_any":null,"type_of_any":4},{".class":"AnyType","missing_import_name":null,"source_any":null,"type_of_any":4}],"type_ref":"typing.Coroutine"},"type_guard":null,"unpack_kwargs":false,"variables":[]}}},"pre_run":{".class":"SymbolTableNode","kind":"Mdef","node":{".class":"FuncDef","abstract_status":0,"arg_kinds":[0,0],"arg_names":["self","call"],"dataclass_transform_spec":null,"flags":[],"fullname":"interactions.models.internal.command.BaseCommand.pre_run","name":"pre_run","type":{".class":"CallableType","arg_kinds":[0,0],"arg_names":["self","call"],"arg_types":["interactions.models.internal.command.BaseCommand",{".class":"CallableType","arg_kinds":[2,4],"arg_names":[null,null],"arg_types":[{".class":"AnyType","missing_import_name":null,"source_any":null,"type_of_any":2},{".class":"AnyType","missing_import_name":null,"source_any":null,"type_of_any":2}],"bound_args":[],"def_extras":{},"fallback":"builtins.function","from_concatenate":false,"implicit":false,"imprecise_arg_kinds":false,"is_ellipsis_args":true,"name":null,"ret_type":{".class":"Instance","args":[{".class":"AnyType","missing_import_name":null,"source_any":null,"type_of_any":4},{".class":"AnyType","missing_import_name":null,"source_any":null,"type_of_any":4},{".class":"AnyType","missing_import_name":null,"source_any":null,"type_of_any":4}],"type_ref":"typing.Coroutine"},"type_guard":null,"unpack_kwargs":false,"variables":[]}],"bound_args":[],"def_extras":{"first_arg":"self"},"fallback":"builtins.function","from_concatenate":false,"implicit":false,"imprecise_arg_kinds":false,"is_ellipsis_args":false,"name":"pre_run of BaseCommand","ret_type":{".class":"CallableType","arg_kinds":[2,4],"arg_names":[null,null],"arg_types":[{".class":"AnyType","missing_import_name":null,"source_any":null,"type_of_any":2},{".class":"AnyType","missing_import_name":null,"source_any":null,"type_of_any":2}],"bound_args":[],"def_extras":{},"fallback":"builtins.function","from_concatenate":false,"implicit":false,"imprecise_arg_kinds":false,"is_ellipsis_args":true,"name":null,"ret_type":{".class":"Instance","args":[{".class":"AnyType","missing_import_name":null,"source_any":null,"type_of_any":4},{".class":"AnyType","missing_import_name":null,"source_any":null,"type_of_any":4},{".class":"AnyType","missing_import_name":null,"source_any":null,"type_of_any":4}],"type_ref":"typing.Coroutine"},"type_guard":null,"unpack_kwargs":false,"variables":[]},"type_guard":null,"unpack_kwargs":false,"variables":[]}}},"pre_run_callback":{".class":"SymbolTableNode","kind":"Mdef","node":{".class":"Var","flags":["is_ready","has_explicit_value"],"fullname":"interactions.models.internal.command.BaseCommand.pre_run_callback","name":"pre_run_callback","type":{".class":"CallableType","arg_kinds":[2,4],"arg_names":[null,null],"arg_types":[{".class":"AnyType","missing_import_name":null,"source_any":null,"type_of_any":2},{".class":"AnyType","missing_import_name":null,"source_any":null,"type_of_any":2}],"bound_args":[],"def_extras":{},"fallback":"builtins.function","from_concatenate":false,"implicit":false,"imprecise_arg_kinds":false,"is_ellipsis_args":true,"name":null,"ret_type":{".class":"Instance","args":[{".class":"AnyType","missing_import_name":null,"source_any":null,"type_of_any":4},{".class":"AnyType","missing_import_name":null,"source_any":null,"type_of_any":4},{".class":"AnyType","missing_import_name":null,"source_any":null,"type_of_any":4}],"type_ref":"typing.Coroutine"},"type_guard":null,"unpack_kwargs":false,"variables":[]}}},"try_convert":{".class":"SymbolTableNode","kind":"Mdef","node":{".class":"FuncDef","abstract_status":0,"arg_kinds":[0,0,0,0],"arg_names":["self","converter","context","value"],"dataclass_transform_spec":null,"flags":["is_coroutine"],"fullname":"interactions.models.internal.command.BaseCommand.try_convert","name":"try_convert","type":{".class":"CallableType","arg_kinds":[0,0,0,0],"arg_names":["self","converter","context","value"],"arg_types":["interactions.models.internal.command.BaseCommand",{".class":"UnionType","items":[{".class":"CallableType","arg_kinds":[2,4],"arg_names":[null,null],"arg_types":[{".class":"AnyType","missing_import_name":null,"source_any":null,"type_of_any":4},{".class":"AnyType","missing_import_name":null,"source_any":null,"type_of_any":4}],"bound_args":[],"def_extras":{},"fallback":"builtins.function","from_concatenate":false,"implicit":false,"imprecise_arg_kinds":false,"is_ellipsis_args":true,"name":null,"ret_type":{".class":"AnyType","missing_import_name":null,"source_any":null,"type_of_any":4},"type_guard":null,"unpack_kwargs":false,"variables":[]},{".class":"NoneType"}]},"interactions.models.internal.context.BaseContext",{".class":"AnyType","missing_import_name":null,"source_any":null,"type_of_any":2}],"bound_args":[],"def_extras":{"first_arg":"self"},"fallback":"builtins.function","from_concatenate":false,"implicit":false,"imprecise_arg_kinds":false,"is_ellipsis_args":false,"name":"try_convert of BaseCommand","ret_type":{".class":"Instance","args":[{".class":"AnyType","missing_import_name":null,"source_any":null,"type_of_any":6},{".class":"AnyType","missing_import_name":null,"source_any":null,"type_of_any":6},{".class":"AnyType","missing_import_name":null,"source_any":null,"type_of_any":2}],"type_ref":"typing.Coroutine"},"type_guard":null,"unpack_kwargs":false,"variables":[]}}}},"self_type":{".class":"TypeVarType","default":{".class":"AnyType","missing_import_name":null,"source_any":null,"type_of_any":4},"fullname":"interactions.models.internal.command.BaseCommand.Self","id":0,"name":"Self","namespace":"","upper_bound":"interactions.models.internal.command.BaseCommand","values":[],"variance":0},"slots":["callback","checks","cooldown","enabled","error_callback","extension","logger","max_concurrency","post_run_callback","pre_run_callback"],"tuple_type":null,"type_vars":[],"typeddict_type":null}},"BaseContext":{".class":"SymbolTableNode","cross_ref":"interactions.models.internal.context.BaseContext","kind":"Gdef","module_public":false},"Buckets":{".class":"SymbolTableNode","cross_ref":"interactions.models.internal.cooldowns.Buckets","kind":"Gdef","module_public":false},"Callable":{".class":"SymbolTableNode","cross_ref":"typing.Callable","kind":"Gdef","module_public":false},"CallbackObject":{".class":"SymbolTableNode","cross_ref":"interactions.models.internal.callback.CallbackObject","kind":"Gdef","module_public":false},"CommandCheckFailure":{".class":"SymbolTableNode","cross_ref":"interactions.client.errors.CommandCheckFailure","kind":"Gdef","module_public":false},"CommandOnCooldown":{".class":"SymbolTableNode","cross_ref":"interactions.client.errors.CommandOnCooldown","kind":"Gdef","module_public":false},"CommandT":{".class":"SymbolTableNode","kind":"Gdef","module_public":false,"node":{".class":"TypeVarExpr","default":{".class":"AnyType","missing_import_name":null,"source_any":null,"type_of_any":4},"fullname":"interactions.models.internal.command.CommandT","name":"CommandT","upper_bound":"builtins.object","values":["interactions.models.internal.command.BaseCommand",{".class":"TypeAliasType","args":[],"type_ref":"interactions.client.const.AsyncCallable"}],"variance":0}},"Converter":{".class":"SymbolTableNode","cross_ref":"interactions.models.internal.protocols.Converter","kind":"Gdef","module_public":false},"Cooldown":{".class":"SymbolTableNode","cross_ref":"interactions.models.internal.cooldowns.Cooldown","kind":"Gdef","module_public":false},"CooldownSystem":{".class":"SymbolTableNode","cross_ref":"interactions.models.internal.cooldowns.CooldownSystem","kind":"Gdef","module_public":false},"Coroutine":{".class":"SymbolTableNode","cross_ref":"typing.Coroutine","kind":"Gdef","module_public":false},"DictSerializationMixin":{".class":"SymbolTableNode","cross_ref":"interactions.client.mixins.serialization.DictSerializationMixin","kind":"Gdef","module_public":false},"Extension":{".class":"SymbolTableNode","cross_ref":"interactions.models.internal.extension.Extension","kind":"Gdef","module_public":false},"MISSING":{".class":"SymbolTableNode","cross_ref":"interactions.client.const.MISSING","kind":"Gdef","module_public":false},"MaxConcurrency":{".class":"SymbolTableNode","cross_ref":"interactions.models.internal.cooldowns.MaxConcurrency","kind":"Gdef","module_public":false},"MaxConcurrencyReached":{".class":"SymbolTableNode","cross_ref":"interactions.client.errors.MaxConcurrencyReached","kind":"Gdef","module_public":false},"Optional":{".class":"SymbolTableNode","cross_ref":"typing.Optional","kind":"Gdef","module_public":false},"TYPE_CHECKING":{".class":"SymbolTableNode","cross_ref":"typing.TYPE_CHECKING","kind":"Gdef","module_public":false},"Tuple":{".class":"SymbolTableNode","cross_ref":"typing.Tuple","kind":"Gdef","module_public":false},"TypeVar":{".class":"SymbolTableNode","cross_ref":"typing.TypeVar","kind":"Gdef","module_public":false},"__all__":{".class":"SymbolTableNode","kind":"Gdef","module_public":false,"node":{".class":"Var","flags":["is_inferred","has_explicit_value"],"fullname":"interactions.models.internal.command.__all__","name":"__all__","type":{".class":"TupleType","implicit":false,"items":["builtins.str","builtins.str","builtins.str","builtins.str"],"partial_fallback":{".class":"Instance","args":[{".class":"AnyType","missing_import_name":null,"source_any":null,"type_of_any":6}],"type_ref":"builtins.tuple"}}}},"__annotations__":{".class":"SymbolTableNode","kind":"Gdef","module_public":false,"node":{".class":"Var","flags":["is_ready"],"fullname":"interactions.models.internal.command.__annotations__","name":"__annotations__","type":{".class":"Instance","args":["builtins.str",{".class":"AnyType","missing_import_name":null,"source_any":null,"type_of_any":6}],"type_ref":"builtins.dict"}}},"__doc__":{".class":"SymbolTableNode","kind":"Gdef","module_public":false,"node":{".class":"Var","flags":["is_ready"],"fullname":"interactions.models.internal.command.__doc__","name":"__doc__","type":"builtins.str"}},"__file__":{".class":"SymbolTableNode","kind":"Gdef","module_public":false,"node":{".class":"Var","flags":["is_ready"],"fullname":"interactions.models.internal.command.__file__","name":"__file__","type":"builtins.str"}},"__name__":{".class":"SymbolTableNode","kind":"Gdef","module_public":false,"node":{".class":"Var","flags":["is_ready"],"fullname":"interactions.models.internal.command.__name__","name":"__name__","type":"builtins.str"}},"__package__":{".class":"SymbolTableNode","kind":"Gdef","module_public":false,"node":{".class":"Var","flags":["is_ready"],"fullname":"interactions.models.internal.command.__package__","name":"__package__","type":"builtins.str"}},"annotations":{".class":"SymbolTableNode","cross_ref":"__future__.annotations","kind":"Gdef","module_public":false},"asyncio":{".class":"SymbolTableNode","cross_ref":"asyncio","kind":"Gdef","module_public":false},"attrs":{".class":"SymbolTableNode","cross_ref":"attrs","kind":"Gdef","module_public":false},"check":{".class":"SymbolTableNode","kind":"Gdef","node":{".class":"FuncDef","abstract_status":0,"arg_kinds":[0],"arg_names":["check"],"dataclass_transform_spec":null,"flags":[],"fullname":"interactions.models.internal.command.check","name":"check","type":{".class":"CallableType","arg_kinds":[0],"arg_names":["check"],"arg_types":[{".class":"CallableType","arg_kinds":[2,4],"arg_names":[null,null],"arg_types":[{".class":"AnyType","missing_import_name":null,"source_any":null,"type_of_any":2},{".class":"AnyType","missing_import_name":null,"source_any":null,"type_of_any":2}],"bound_args":[],"def_extras":{},"fallback":"builtins.function","from_concatenate":false,"implicit":false,"imprecise_arg_kinds":false,"is_ellipsis_args":true,"name":null,"ret_type":{".class":"Instance","args":["builtins.bool"],"type_ref":"typing.Awaitable"},"type_guard":null,"unpack_kwargs":false,"variables":[]}],"bound_args":[],"def_extras":{"first_arg":null},"fallback":"builtins.function","from_concatenate":false,"implicit":false,"imprecise_arg_kinds":false,"is_ellipsis_args":false,"name":"check","ret_type":{".class":"CallableType","arg_kinds":[0],"arg_names":[null],"arg_types":[{".class":"TypeVarType","default":{".class":"AnyType","missing_import_name":null,"source_any":null,"type_of_any":4},"fullname":"interactions.models.internal.command.CommandT","id":-1,"name":"CommandT","namespace":"","upper_bound":"builtins.object","values":["interactions.models.internal.command.BaseCommand",{".class":"TypeAliasType","args":[],"type_ref":"interactions.client.const.AsyncCallable"}],"variance":0}],"bound_args":[],"def_extras":{},"fallback":"builtins.function","from_concatenate":false,"implicit":false,"imprecise_arg_kinds":false,"is_ellipsis_args":false,"name":null,"ret_type":{".class":"TypeVarType","default":{".class":"AnyType","missing_import_name":null,"source_any":null,"type_of_any":4},"fullname":"interactions.models.internal.command.CommandT","id":-1,"name":"CommandT","namespace":"","upper_bound":"builtins.object","values":["interactions.models.internal.command.BaseCommand",{".class":"TypeAliasType","args":[],"type_ref":"interactions.client.const.AsyncCallable"}],"variance":0},"type_guard":null,"unpack_kwargs":false,"variables":[{".class":"TypeVarType","default":{".class":"AnyType","missing_import_name":null,"source_any":null,"type_of_any":4},"fullname":"interactions.models.internal.command.CommandT","id":-1,"name":"CommandT","namespace":"","upper_bound":"builtins.object","values":["interactions.models.internal.command.BaseCommand",{".class":"TypeAliasType","args":[],"type_ref":"interactions.client.const.AsyncCallable"}],"variance":0}]},"type_guard":null,"unpack_kwargs":false,"variables":[]}}},"cooldown":{".class":"SymbolTableNode","kind":"Gdef","node":{".class":"FuncDef","abstract_status":0,"arg_kinds":[0,0,0,1],"arg_names":["bucket","rate","interval","cooldown_system"],"dataclass_transform_spec":null,"flags":[],"fullname":"interactions.models.internal.command.cooldown","name":"cooldown","type":{".class":"CallableType","arg_kinds":[0,0,0,1],"arg_names":["bucket","rate","interval","cooldown_system"],"arg_types":["interactions.models.internal.cooldowns.Buckets","builtins.int","builtins.float",{".class":"UnionType","items":[{".class":"TypeType","item":"interactions.models.internal.cooldowns.CooldownSystem"},{".class":"NoneType"}]}],"bound_args":[],"def_extras":{"first_arg":null},"fallback":"builtins.function","from_concatenate":false,"implicit":false,"imprecise_arg_kinds":false,"is_ellipsis_args":false,"name":"cooldown","ret_type":{".class":"CallableType","arg_kinds":[0],"arg_names":[null],"arg_types":[{".class":"TypeVarType","default":{".class":"AnyType","missing_import_name":null,"source_any":null,"type_of_any":4},"fullname":"interactions.models.internal.command.CommandT","id":-1,"name":"CommandT","namespace":"","upper_bound":"builtins.object","values":["interactions.models.internal.command.BaseCommand",{".class":"TypeAliasType","args":[],"type_ref":"interactions.client.const.AsyncCallable"}],"variance":0}],"bound_args":[],"def_extras":{},"fallback":"builtins.function","from_concatenate":false,"implicit":false,"imprecise_arg_kinds":false,"is_ellipsis_args":false,"name":null,"ret_type":{".class":"TypeVarType","default":{".class":"AnyType","missing_import_name":null,"source_any":null,"type_of_any":4},"fullname":"interactions.models.internal.command.CommandT","id":-1,"name":"CommandT","namespace":"","upper_bound":"builtins.object","values":["interactions.models.internal.command.BaseCommand",{".class":"TypeAliasType","args":[],"type_ref":"interactions.client.const.AsyncCallable"}],"variance":0},"type_guard":null,"unpack_kwargs":false,"variables":[{".class":"TypeVarType","default":{".class":"AnyType","missing_import_name":null,"source_any":null,"type_of_any":4},"fullname":"interactions.models.internal.command.CommandT","id":-1,"name":"CommandT","namespace":"","upper_bound":"builtins.object","values":["interactions.models.internal.command.BaseCommand",{".class":"TypeAliasType","args":[],"type_ref":"interactions.client.const.AsyncCallable"}],"variance":0}]},"type_guard":null,"unpack_kwargs":false,"variables":[]}}},"docs":{".class":"SymbolTableNode","cross_ref":"interactions.client.utils.attr_utils.docs","kind":"Gdef","module_public":false},"get_object_name":{".class":"SymbolTableNode","cross_ref":"interactions.client.utils.misc_utils.get_object_name","kind":"Gdef","module_public":false},"get_parameters":{".class":"SymbolTableNode","cross_ref":"interactions.client.utils.misc_utils.get_parameters","kind":"Gdef","module_public":false},"max_concurrency":{".class":"SymbolTableNode","kind":"Gdef","node":{".class":"FuncDef","abstract_status":0,"arg_kinds":[0,0],"arg_names":["bucket","concurrent"],"dataclass_transform_spec":null,"flags":[],"fullname":"interactions.models.internal.command.max_concurrency","name":"max_concurrency","type":{".class":"CallableType","arg_kinds":[0,0],"arg_names":["bucket","concurrent"],"arg_types":["interactions.models.internal.cooldowns.Buckets","builtins.int"],"bound_args":[],"def_extras":{"first_arg":null},"fallback":"builtins.function","from_concatenate":false,"implicit":false,"imprecise_arg_kinds":false,"is_ellipsis_args":false,"name":"max_concurrency","ret_type":{".class":"CallableType","arg_kinds":[0],"arg_names":[null],"arg_types":[{".class":"TypeVarType","default":{".class":"AnyType","missing_import_name":null,"source_any":null,"type_of_any":4},"fullname":"interactions.models.internal.command.CommandT","id":-1,"name":"CommandT","namespace":"","upper_bound":"builtins.object","values":["interactions.models.internal.command.BaseCommand",{".class":"TypeAliasType","args":[],"type_ref":"interactions.client.const.AsyncCallable"}],"variance":0}],"bound_args":[],"def_extras":{},"fallback":"builtins.function","from_concatenate":false,"implicit":false,"imprecise_arg_kinds":false,"is_ellipsis_args":false,"name":null,"ret_type":{".class":"TypeVarType","default":{".class":"AnyType","missing_import_name":null,"source_any":null,"type_of_any":4},"fullname":"interactions.models.internal.command.CommandT","id":-1,"name":"CommandT","namespace":"","upper_bound":"builtins.object","values":["interactions.models.internal.command.BaseCommand",{".class":"TypeAliasType","args":[],"type_ref":"interactions.client.const.AsyncCallable"}],"variance":0},"type_guard":null,"unpack_kwargs":false,"variables":[{".class":"TypeVarType","default":{".class":"AnyType","missing_import_name":null,"source_any":null,"type_of_any":4},"fullname":"interactions.models.internal.command.CommandT","id":-1,"name":"CommandT","namespace":"","upper_bound":"builtins.object","values":["interactions.models.internal.command.BaseCommand",{".class":"TypeAliasType","args":[],"type_ref":"interactions.client.const.AsyncCallable"}],"variance":0}]},"type_guard":null,"unpack_kwargs":false,"variables":[]}}},"maybe_coroutine":{".class":"SymbolTableNode","cross_ref":"interactions.client.utils.misc_utils.maybe_coroutine","kind":"Gdef","module_public":false},"no_export_meta":{".class":"SymbolTableNode","cross_ref":"interactions.client.utils.serializer.no_export_meta","kind":"Gdef","module_public":false},"typing":{".class":"SymbolTableNode","cross_ref":"typing","kind":"Gdef","module_public":false}},"path":"c:\\Python312\\Lib\\site-packages\\interactions\\models\\internal\\command.py"}