{".class":"MypyFile","_fullname":"discord.ui.item","future_import_flags":["annotations"],"is_partial_stub_package":false,"is_stub":false,"names":{".class":"SymbolTable","Any":{".class":"SymbolTableNode","cross_ref":"typing.Any","kind":"Gdef","module_public":false},"Callable":{".class":"SymbolTableNode","cross_ref":"typing.Callable","kind":"Gdef","module_public":false},"ClientT":{".class":"SymbolTableNode","cross_ref":"discord._types.ClientT","kind":"Gdef","module_public":false},"Component":{".class":"SymbolTableNode","cross_ref":"discord.components.Component","kind":"Gdef","module_public":false},"ComponentType":{".class":"SymbolTableNode","cross_ref":"discord.enums.ComponentType","kind":"Gdef","module_public":false},"Coroutine":{".class":"SymbolTableNode","cross_ref":"typing.Coroutine","kind":"Gdef","module_public":false},"Dict":{".class":"SymbolTableNode","cross_ref":"typing.Dict","kind":"Gdef","module_public":false},"Generic":{".class":"SymbolTableNode","cross_ref":"typing.Generic","kind":"Gdef","module_public":false},"I":{".class":"SymbolTableNode","kind":"Gdef","module_public":false,"node":{".class":"TypeVarExpr","default":{".class":"AnyType","missing_import_name":null,"source_any":null,"type_of_any":4},"fullname":"discord.ui.item.I","name":"I","upper_bound":{".class":"Instance","args":[{".class":"AnyType","missing_import_name":null,"source_any":null,"type_of_any":2}],"type_ref":"discord.ui.item.Item"},"values":[],"variance":0}},"Interaction":{".class":"SymbolTableNode","cross_ref":"discord.interactions.Interaction","kind":"Gdef","module_public":false},"Item":{".class":"SymbolTableNode","kind":"Gdef","node":{".class":"TypeInfo","_promote":[],"abstract_attributes":[],"alt_promote":null,"bases":["builtins.object"],"dataclass_transform_spec":null,"declared_metaclass":null,"defn":{".class":"ClassDef","fullname":"discord.ui.item.Item","name":"Item","type_vars":[{".class":"TypeVarType","default":{".class":"AnyType","missing_import_name":null,"source_any":null,"type_of_any":4},"fullname":"discord.ui.item.V","id":1,"name":"V","namespace":"discord.ui.item.Item","upper_bound":"discord.ui.view.View","values":[],"variance":1}]},"deletable_attributes":[],"flags":[],"fullname":"discord.ui.item.Item","has_param_spec_type":false,"metaclass_type":null,"metadata":{},"module_name":"discord.ui.item","mro":["discord.ui.item.Item","builtins.object"],"names":{".class":"SymbolTable","__init__":{".class":"SymbolTableNode","kind":"Mdef","node":{".class":"FuncDef","abstract_status":0,"arg_kinds":[0],"arg_names":["self"],"dataclass_transform_spec":null,"flags":[],"fullname":"discord.ui.item.Item.__init__","name":"__init__","type":null}},"__item_repr_attributes__":{".class":"SymbolTableNode","kind":"Mdef","node":{".class":"Var","flags":["is_initialized_in_class","is_ready","has_explicit_value"],"fullname":"discord.ui.item.Item.__item_repr_attributes__","name":"__item_repr_attributes__","type":{".class":"Instance","args":["builtins.str"],"type_ref":"builtins.tuple"}}},"__repr__":{".class":"SymbolTableNode","kind":"Mdef","node":{".class":"FuncDef","abstract_status":0,"arg_kinds":[0],"arg_names":[null],"dataclass_transform_spec":null,"flags":[],"fullname":"discord.ui.item.Item.__repr__","name":"__repr__","type":{".class":"CallableType","arg_kinds":[0],"arg_names":[null],"arg_types":[{".class":"Instance","args":[{".class":"TypeVarType","default":{".class":"AnyType","missing_import_name":null,"source_any":null,"type_of_any":4},"fullname":"discord.ui.item.V","id":1,"name":"V","namespace":"discord.ui.item.Item","upper_bound":"discord.ui.view.View","values":[],"variance":1}],"type_ref":"discord.ui.item.Item"}],"bound_args":[],"def_extras":{"first_arg":"self"},"fallback":"builtins.function","from_concatenate":false,"implicit":false,"imprecise_arg_kinds":false,"is_ellipsis_args":false,"name":"__repr__ of Item","ret_type":"builtins.str","type_guard":null,"unpack_kwargs":false,"variables":[]}}},"_provided_custom_id":{".class":"SymbolTableNode","implicit":true,"kind":"Mdef","node":{".class":"Var","flags":["explicit_self_type","is_ready","is_inferred"],"fullname":"discord.ui.item.Item._provided_custom_id","name":"_provided_custom_id","type":"builtins.bool"}},"_refresh_component":{".class":"SymbolTableNode","kind":"Mdef","node":{".class":"FuncDef","abstract_status":0,"arg_kinds":[0,0],"arg_names":["self","component"],"dataclass_transform_spec":null,"flags":[],"fullname":"discord.ui.item.Item._refresh_component","name":"_refresh_component","type":{".class":"CallableType","arg_kinds":[0,0],"arg_names":["self","component"],"arg_types":[{".class":"Instance","args":[{".class":"TypeVarType","default":{".class":"AnyType","missing_import_name":null,"source_any":null,"type_of_any":4},"fullname":"discord.ui.item.V","id":1,"name":"V","namespace":"discord.ui.item.Item","upper_bound":"discord.ui.view.View","values":[],"variance":1}],"type_ref":"discord.ui.item.Item"},"discord.components.Component"],"bound_args":[],"def_extras":{"first_arg":"self"},"fallback":"builtins.function","from_concatenate":false,"implicit":false,"imprecise_arg_kinds":false,"is_ellipsis_args":false,"name":"_refresh_component of Item","ret_type":{".class":"NoneType"},"type_guard":null,"unpack_kwargs":false,"variables":[]}}},"_refresh_state":{".class":"SymbolTableNode","kind":"Mdef","node":{".class":"FuncDef","abstract_status":0,"arg_kinds":[0,0,0],"arg_names":["self","interaction","data"],"dataclass_transform_spec":null,"flags":[],"fullname":"discord.ui.item.Item._refresh_state","name":"_refresh_state","type":{".class":"CallableType","arg_kinds":[0,0,0],"arg_names":["self","interaction","data"],"arg_types":[{".class":"Instance","args":[{".class":"TypeVarType","default":{".class":"AnyType","missing_import_name":null,"source_any":null,"type_of_any":4},"fullname":"discord.ui.item.V","id":1,"name":"V","namespace":"discord.ui.item.Item","upper_bound":"discord.ui.view.View","values":[],"variance":1}],"type_ref":"discord.ui.item.Item"},{".class":"Instance","args":[{".class":"AnyType","missing_import_name":null,"source_any":null,"type_of_any":4}],"type_ref":"discord.interactions.Interaction"},{".class":"Instance","args":["builtins.str",{".class":"AnyType","missing_import_name":null,"source_any":null,"type_of_any":2}],"type_ref":"builtins.dict"}],"bound_args":[],"def_extras":{"first_arg":"self"},"fallback":"builtins.function","from_concatenate":false,"implicit":false,"imprecise_arg_kinds":false,"is_ellipsis_args":false,"name":"_refresh_state of Item","ret_type":{".class":"NoneType"},"type_guard":null,"unpack_kwargs":false,"variables":[]}}},"_rendered_row":{".class":"SymbolTableNode","implicit":true,"kind":"Mdef","node":{".class":"Var","flags":["explicit_self_type","is_ready","is_inferred"],"fullname":"discord.ui.item.Item._rendered_row","name":"_rendered_row","type":{".class":"UnionType","items":["builtins.int",{".class":"NoneType"}]}}},"_row":{".class":"SymbolTableNode","implicit":true,"kind":"Mdef","node":{".class":"Var","flags":["explicit_self_type","is_ready","is_inferred"],"fullname":"discord.ui.item.Item._row","name":"_row","type":{".class":"UnionType","items":["builtins.int",{".class":"NoneType"}]}}},"_view":{".class":"SymbolTableNode","implicit":true,"kind":"Mdef","node":{".class":"Var","flags":["explicit_self_type","is_ready","is_inferred"],"fullname":"discord.ui.item.Item._view","name":"_view","type":{".class":"UnionType","items":[{".class":"TypeVarType","default":{".class":"AnyType","missing_import_name":null,"source_any":null,"type_of_any":4},"fullname":"discord.ui.item.V","id":1,"name":"V","namespace":"discord.ui.item.Item","upper_bound":"discord.ui.view.View","values":[],"variance":1},{".class":"NoneType"}]}}},"callback":{".class":"SymbolTableNode","kind":"Mdef","node":{".class":"FuncDef","abstract_status":0,"arg_kinds":[0,0],"arg_names":["self","interaction"],"dataclass_transform_spec":null,"flags":["is_coroutine"],"fullname":"discord.ui.item.Item.callback","name":"callback","type":{".class":"CallableType","arg_kinds":[0,0],"arg_names":["self","interaction"],"arg_types":[{".class":"Instance","args":[{".class":"TypeVarType","default":{".class":"AnyType","missing_import_name":null,"source_any":null,"type_of_any":4},"fullname":"discord.ui.item.V","id":1,"name":"V","namespace":"discord.ui.item.Item","upper_bound":"discord.ui.view.View","values":[],"variance":1}],"type_ref":"discord.ui.item.Item"},{".class":"Instance","args":[{".class":"TypeVarType","default":"discord.client.Client","fullname":"discord._types.ClientT","id":-1,"name":"ClientT","namespace":"","upper_bound":"discord.client.Client","values":[],"variance":1}],"type_ref":"discord.interactions.Interaction"}],"bound_args":[],"def_extras":{"first_arg":"self"},"fallback":"builtins.function","from_concatenate":false,"implicit":false,"imprecise_arg_kinds":false,"is_ellipsis_args":false,"name":"callback of Item","ret_type":{".class":"Instance","args":[{".class":"AnyType","missing_import_name":null,"source_any":null,"type_of_any":6},{".class":"AnyType","missing_import_name":null,"source_any":null,"type_of_any":6},{".class":"AnyType","missing_import_name":null,"source_any":null,"type_of_any":2}],"type_ref":"typing.Coroutine"},"type_guard":null,"unpack_kwargs":false,"variables":[{".class":"TypeVarType","default":"discord.client.Client","fullname":"discord._types.ClientT","id":-1,"name":"ClientT","namespace":"","upper_bound":"discord.client.Client","values":[],"variance":1}]}}},"from_component":{".class":"SymbolTableNode","kind":"Mdef","node":{".class":"Decorator","func":{".class":"FuncDef","abstract_status":0,"arg_kinds":[0,0],"arg_names":["cls","component"],"dataclass_transform_spec":null,"flags":["is_class","is_decorated"],"fullname":"discord.ui.item.Item.from_component","name":"from_component","type":{".class":"CallableType","arg_kinds":[0,0],"arg_names":["cls","component"],"arg_types":[{".class":"TypeType","item":{".class":"TypeVarType","default":{".class":"AnyType","missing_import_name":null,"source_any":null,"type_of_any":4},"fullname":"discord.ui.item.I","id":-1,"name":"I","namespace":"","upper_bound":{".class":"Instance","args":[{".class":"AnyType","missing_import_name":null,"source_any":null,"type_of_any":2}],"type_ref":"discord.ui.item.Item"},"values":[],"variance":0}},"discord.components.Component"],"bound_args":[],"def_extras":{"first_arg":"cls"},"fallback":"builtins.function","from_concatenate":false,"implicit":false,"imprecise_arg_kinds":false,"is_ellipsis_args":false,"name":"from_component of Item","ret_type":{".class":"TypeVarType","default":{".class":"AnyType","missing_import_name":null,"source_any":null,"type_of_any":4},"fullname":"discord.ui.item.I","id":-1,"name":"I","namespace":"","upper_bound":{".class":"Instance","args":[{".class":"AnyType","missing_import_name":null,"source_any":null,"type_of_any":2}],"type_ref":"discord.ui.item.Item"},"values":[],"variance":0},"type_guard":null,"unpack_kwargs":false,"variables":[{".class":"TypeVarType","default":{".class":"AnyType","missing_import_name":null,"source_any":null,"type_of_any":4},"fullname":"discord.ui.item.I","id":-1,"name":"I","namespace":"","upper_bound":{".class":"Instance","args":[{".class":"AnyType","missing_import_name":null,"source_any":null,"type_of_any":2}],"type_ref":"discord.ui.item.Item"},"values":[],"variance":0}]}},"is_overload":false,"var":{".class":"Var","flags":["is_initialized_in_class","is_classmethod","is_ready","is_inferred"],"fullname":"discord.ui.item.Item.from_component","name":"from_component","type":{".class":"CallableType","arg_kinds":[0,0],"arg_names":["cls","component"],"arg_types":[{".class":"TypeType","item":{".class":"TypeVarType","default":{".class":"AnyType","missing_import_name":null,"source_any":null,"type_of_any":4},"fullname":"discord.ui.item.I","id":-1,"name":"I","namespace":"","upper_bound":{".class":"Instance","args":[{".class":"AnyType","missing_import_name":null,"source_any":null,"type_of_any":2}],"type_ref":"discord.ui.item.Item"},"values":[],"variance":0}},"discord.components.Component"],"bound_args":[],"def_extras":{"first_arg":"cls"},"fallback":"builtins.function","from_concatenate":false,"implicit":false,"imprecise_arg_kinds":false,"is_ellipsis_args":false,"name":"from_component of Item","ret_type":{".class":"TypeVarType","default":{".class":"AnyType","missing_import_name":null,"source_any":null,"type_of_any":4},"fullname":"discord.ui.item.I","id":-1,"name":"I","namespace":"","upper_bound":{".class":"Instance","args":[{".class":"AnyType","missing_import_name":null,"source_any":null,"type_of_any":2}],"type_ref":"discord.ui.item.Item"},"values":[],"variance":0},"type_guard":null,"unpack_kwargs":false,"variables":[{".class":"TypeVarType","default":{".class":"AnyType","missing_import_name":null,"source_any":null,"type_of_any":4},"fullname":"discord.ui.item.I","id":-1,"name":"I","namespace":"","upper_bound":{".class":"Instance","args":[{".class":"AnyType","missing_import_name":null,"source_any":null,"type_of_any":2}],"type_ref":"discord.ui.item.Item"},"values":[],"variance":0}]}}}},"is_dispatchable":{".class":"SymbolTableNode","kind":"Mdef","node":{".class":"FuncDef","abstract_status":0,"arg_kinds":[0],"arg_names":["self"],"dataclass_transform_spec":null,"flags":[],"fullname":"discord.ui.item.Item.is_dispatchable","name":"is_dispatchable","type":{".class":"CallableType","arg_kinds":[0],"arg_names":["self"],"arg_types":[{".class":"Instance","args":[{".class":"TypeVarType","default":{".class":"AnyType","missing_import_name":null,"source_any":null,"type_of_any":4},"fullname":"discord.ui.item.V","id":1,"name":"V","namespace":"discord.ui.item.Item","upper_bound":"discord.ui.view.View","values":[],"variance":1}],"type_ref":"discord.ui.item.Item"}],"bound_args":[],"def_extras":{"first_arg":"self"},"fallback":"builtins.function","from_concatenate":false,"implicit":false,"imprecise_arg_kinds":false,"is_ellipsis_args":false,"name":"is_dispatchable of Item","ret_type":"builtins.bool","type_guard":null,"unpack_kwargs":false,"variables":[]}}},"is_persistent":{".class":"SymbolTableNode","kind":"Mdef","node":{".class":"FuncDef","abstract_status":0,"arg_kinds":[0],"arg_names":["self"],"dataclass_transform_spec":null,"flags":[],"fullname":"discord.ui.item.Item.is_persistent","name":"is_persistent","type":{".class":"CallableType","arg_kinds":[0],"arg_names":["self"],"arg_types":[{".class":"Instance","args":[{".class":"TypeVarType","default":{".class":"AnyType","missing_import_name":null,"source_any":null,"type_of_any":4},"fullname":"discord.ui.item.V","id":1,"name":"V","namespace":"discord.ui.item.Item","upper_bound":"discord.ui.view.View","values":[],"variance":1}],"type_ref":"discord.ui.item.Item"}],"bound_args":[],"def_extras":{"first_arg":"self"},"fallback":"builtins.function","from_concatenate":false,"implicit":false,"imprecise_arg_kinds":false,"is_ellipsis_args":false,"name":"is_persistent of Item","ret_type":"builtins.bool","type_guard":null,"unpack_kwargs":false,"variables":[]}}},"row":{".class":"SymbolTableNode","kind":"Mdef","node":{".class":"OverloadedFuncDef","flags":["is_property"],"fullname":"discord.ui.item.Item.row","impl":null,"items":[{".class":"Decorator","func":{".class":"FuncDef","abstract_status":0,"arg_kinds":[0],"arg_names":["self"],"dataclass_transform_spec":null,"flags":["is_property","is_overload","is_decorated"],"fullname":"discord.ui.item.Item.row","name":"row","type":{".class":"CallableType","arg_kinds":[0],"arg_names":["self"],"arg_types":[{".class":"Instance","args":[{".class":"TypeVarType","default":{".class":"AnyType","missing_import_name":null,"source_any":null,"type_of_any":4},"fullname":"discord.ui.item.V","id":1,"name":"V","namespace":"discord.ui.item.Item","upper_bound":"discord.ui.view.View","values":[],"variance":1}],"type_ref":"discord.ui.item.Item"}],"bound_args":[],"def_extras":{"first_arg":"self"},"fallback":"builtins.function","from_concatenate":false,"implicit":false,"imprecise_arg_kinds":false,"is_ellipsis_args":false,"name":"row of Item","ret_type":{".class":"UnionType","items":["builtins.int",{".class":"NoneType"}]},"type_guard":null,"unpack_kwargs":false,"variables":[]}},"is_overload":true,"var":{".class":"Var","flags":["is_initialized_in_class","is_property","is_settable_property","is_ready","is_inferred"],"fullname":"discord.ui.item.Item.row","name":"row","type":{".class":"CallableType","arg_kinds":[0],"arg_names":["self"],"arg_types":[{".class":"Instance","args":[{".class":"TypeVarType","default":{".class":"AnyType","missing_import_name":null,"source_any":null,"type_of_any":4},"fullname":"discord.ui.item.V","id":1,"name":"V","namespace":"discord.ui.item.Item","upper_bound":"discord.ui.view.View","values":[],"variance":1}],"type_ref":"discord.ui.item.Item"}],"bound_args":[],"def_extras":{"first_arg":"self"},"fallback":"builtins.function","from_concatenate":false,"implicit":false,"imprecise_arg_kinds":false,"is_ellipsis_args":false,"name":"row of Item","ret_type":{".class":"UnionType","items":["builtins.int",{".class":"NoneType"}]},"type_guard":null,"unpack_kwargs":false,"variables":[]}}},{".class":"Decorator","func":{".class":"FuncDef","abstract_status":0,"arg_kinds":[0,0],"arg_names":["self","value"],"dataclass_transform_spec":null,"flags":["is_decorated"],"fullname":"discord.ui.item.Item.row","name":"row","type":{".class":"CallableType","arg_kinds":[0,0],"arg_names":["self","value"],"arg_types":[{".class":"Instance","args":[{".class":"TypeVarType","default":{".class":"AnyType","missing_import_name":null,"source_any":null,"type_of_any":4},"fullname":"discord.ui.item.V","id":1,"name":"V","namespace":"discord.ui.item.Item","upper_bound":"discord.ui.view.View","values":[],"variance":1}],"type_ref":"discord.ui.item.Item"},{".class":"UnionType","items":["builtins.int",{".class":"NoneType"}]}],"bound_args":[],"def_extras":{"first_arg":"self"},"fallback":"builtins.function","from_concatenate":false,"implicit":false,"imprecise_arg_kinds":false,"is_ellipsis_args":false,"name":"row of Item","ret_type":{".class":"NoneType"},"type_guard":null,"unpack_kwargs":false,"variables":[]}},"is_overload":false,"var":{".class":"Var","flags":["is_inferred"],"fullname":"","name":"row","type":null}}],"type":{".class":"Overloaded","items":[{".class":"CallableType","arg_kinds":[0],"arg_names":["self"],"arg_types":[{".class":"Instance","args":[{".class":"TypeVarType","default":{".class":"AnyType","missing_import_name":null,"source_any":null,"type_of_any":4},"fullname":"discord.ui.item.V","id":1,"name":"V","namespace":"discord.ui.item.Item","upper_bound":"discord.ui.view.View","values":[],"variance":1}],"type_ref":"discord.ui.item.Item"}],"bound_args":[],"def_extras":{"first_arg":"self"},"fallback":"builtins.function","from_concatenate":false,"implicit":false,"imprecise_arg_kinds":false,"is_ellipsis_args":false,"name":"row of Item","ret_type":{".class":"UnionType","items":["builtins.int",{".class":"NoneType"}]},"type_guard":null,"unpack_kwargs":false,"variables":[]}]}}},"to_component_dict":{".class":"SymbolTableNode","kind":"Mdef","node":{".class":"FuncDef","abstract_status":0,"arg_kinds":[0],"arg_names":["self"],"dataclass_transform_spec":null,"flags":[],"fullname":"discord.ui.item.Item.to_component_dict","name":"to_component_dict","type":{".class":"CallableType","arg_kinds":[0],"arg_names":["self"],"arg_types":[{".class":"Instance","args":[{".class":"TypeVarType","default":{".class":"AnyType","missing_import_name":null,"source_any":null,"type_of_any":4},"fullname":"discord.ui.item.V","id":1,"name":"V","namespace":"discord.ui.item.Item","upper_bound":"discord.ui.view.View","values":[],"variance":1}],"type_ref":"discord.ui.item.Item"}],"bound_args":[],"def_extras":{"first_arg":"self"},"fallback":"builtins.function","from_concatenate":false,"implicit":false,"imprecise_arg_kinds":false,"is_ellipsis_args":false,"name":"to_component_dict of Item","ret_type":{".class":"Instance","args":["builtins.str",{".class":"AnyType","missing_import_name":null,"source_any":null,"type_of_any":2}],"type_ref":"builtins.dict"},"type_guard":null,"unpack_kwargs":false,"variables":[]}}},"type":{".class":"SymbolTableNode","kind":"Mdef","node":{".class":"Decorator","func":{".class":"FuncDef","abstract_status":0,"arg_kinds":[0],"arg_names":["self"],"dataclass_transform_spec":null,"flags":["is_property","is_decorated"],"fullname":"discord.ui.item.Item.type","name":"type","type":{".class":"CallableType","arg_kinds":[0],"arg_names":["self"],"arg_types":[{".class":"Instance","args":[{".class":"TypeVarType","default":{".class":"AnyType","missing_import_name":null,"source_any":null,"type_of_any":4},"fullname":"discord.ui.item.V","id":1,"name":"V","namespace":"discord.ui.item.Item","upper_bound":"discord.ui.view.View","values":[],"variance":1}],"type_ref":"discord.ui.item.Item"}],"bound_args":[],"def_extras":{"first_arg":"self"},"fallback":"builtins.function","from_concatenate":false,"implicit":false,"imprecise_arg_kinds":false,"is_ellipsis_args":false,"name":"type of Item","ret_type":"discord.enums.ComponentType","type_guard":null,"unpack_kwargs":false,"variables":[]}},"is_overload":false,"var":{".class":"Var","flags":["is_initialized_in_class","is_property","is_ready","is_inferred"],"fullname":"discord.ui.item.Item.type","name":"type","type":{".class":"CallableType","arg_kinds":[0],"arg_names":["self"],"arg_types":[{".class":"Instance","args":[{".class":"TypeVarType","default":{".class":"AnyType","missing_import_name":null,"source_any":null,"type_of_any":4},"fullname":"discord.ui.item.V","id":1,"name":"V","namespace":"discord.ui.item.Item","upper_bound":"discord.ui.view.View","values":[],"variance":1}],"type_ref":"discord.ui.item.Item"}],"bound_args":[],"def_extras":{"first_arg":"self"},"fallback":"builtins.function","from_concatenate":false,"implicit":false,"imprecise_arg_kinds":false,"is_ellipsis_args":false,"name":"type of Item","ret_type":"discord.enums.ComponentType","type_guard":null,"unpack_kwargs":false,"variables":[]}}}},"view":{".class":"SymbolTableNode","kind":"Mdef","node":{".class":"Decorator","func":{".class":"FuncDef","abstract_status":0,"arg_kinds":[0],"arg_names":["self"],"dataclass_transform_spec":null,"flags":["is_property","is_decorated"],"fullname":"discord.ui.item.Item.view","name":"view","type":{".class":"CallableType","arg_kinds":[0],"arg_names":["self"],"arg_types":[{".class":"Instance","args":[{".class":"TypeVarType","default":{".class":"AnyType","missing_import_name":null,"source_any":null,"type_of_any":4},"fullname":"discord.ui.item.V","id":1,"name":"V","namespace":"discord.ui.item.Item","upper_bound":"discord.ui.view.View","values":[],"variance":1}],"type_ref":"discord.ui.item.Item"}],"bound_args":[],"def_extras":{"first_arg":"self"},"fallback":"builtins.function","from_concatenate":false,"implicit":false,"imprecise_arg_kinds":false,"is_ellipsis_args":false,"name":"view of Item","ret_type":{".class":"UnionType","items":[{".class":"TypeVarType","default":{".class":"AnyType","missing_import_name":null,"source_any":null,"type_of_any":4},"fullname":"discord.ui.item.V","id":1,"name":"V","namespace":"discord.ui.item.Item","upper_bound":"discord.ui.view.View","values":[],"variance":1},{".class":"NoneType"}]},"type_guard":null,"unpack_kwargs":false,"variables":[]}},"is_overload":false,"var":{".class":"Var","flags":["is_initialized_in_class","is_property","is_ready","is_inferred"],"fullname":"discord.ui.item.Item.view","name":"view","type":{".class":"CallableType","arg_kinds":[0],"arg_names":["self"],"arg_types":[{".class":"Instance","args":[{".class":"TypeVarType","default":{".class":"AnyType","missing_import_name":null,"source_any":null,"type_of_any":4},"fullname":"discord.ui.item.V","id":1,"name":"V","namespace":"discord.ui.item.Item","upper_bound":"discord.ui.view.View","values":[],"variance":1}],"type_ref":"discord.ui.item.Item"}],"bound_args":[],"def_extras":{"first_arg":"self"},"fallback":"builtins.function","from_concatenate":false,"implicit":false,"imprecise_arg_kinds":false,"is_ellipsis_args":false,"name":"view of Item","ret_type":{".class":"UnionType","items":[{".class":"TypeVarType","default":{".class":"AnyType","missing_import_name":null,"source_any":null,"type_of_any":4},"fullname":"discord.ui.item.V","id":1,"name":"V","namespace":"discord.ui.item.Item","upper_bound":"discord.ui.view.View","values":[],"variance":1},{".class":"NoneType"}]},"type_guard":null,"unpack_kwargs":false,"variables":[]}}}},"width":{".class":"SymbolTableNode","kind":"Mdef","node":{".class":"Decorator","func":{".class":"FuncDef","abstract_status":0,"arg_kinds":[0],"arg_names":["self"],"dataclass_transform_spec":null,"flags":["is_property","is_decorated"],"fullname":"discord.ui.item.Item.width","name":"width","type":{".class":"CallableType","arg_kinds":[0],"arg_names":["self"],"arg_types":[{".class":"Instance","args":[{".class":"TypeVarType","default":{".class":"AnyType","missing_import_name":null,"source_any":null,"type_of_any":4},"fullname":"discord.ui.item.V","id":1,"name":"V","namespace":"discord.ui.item.Item","upper_bound":"discord.ui.view.View","values":[],"variance":1}],"type_ref":"discord.ui.item.Item"}],"bound_args":[],"def_extras":{"first_arg":"self"},"fallback":"builtins.function","from_concatenate":false,"implicit":false,"imprecise_arg_kinds":false,"is_ellipsis_args":false,"name":"width of Item","ret_type":"builtins.int","type_guard":null,"unpack_kwargs":false,"variables":[]}},"is_overload":false,"var":{".class":"Var","flags":["is_initialized_in_class","is_property","is_ready","is_inferred"],"fullname":"discord.ui.item.Item.width","name":"width","type":{".class":"CallableType","arg_kinds":[0],"arg_names":["self"],"arg_types":[{".class":"Instance","args":[{".class":"TypeVarType","default":{".class":"AnyType","missing_import_name":null,"source_any":null,"type_of_any":4},"fullname":"discord.ui.item.V","id":1,"name":"V","namespace":"discord.ui.item.Item","upper_bound":"discord.ui.view.View","values":[],"variance":1}],"type_ref":"discord.ui.item.Item"}],"bound_args":[],"def_extras":{"first_arg":"self"},"fallback":"builtins.function","from_concatenate":false,"implicit":false,"imprecise_arg_kinds":false,"is_ellipsis_args":false,"name":"width of Item","ret_type":"builtins.int","type_guard":null,"unpack_kwargs":false,"variables":[]}}}}},"self_type":{".class":"TypeVarType","default":{".class":"AnyType","missing_import_name":null,"source_any":null,"type_of_any":4},"fullname":"discord.ui.item.Item.Self","id":0,"name":"Self","namespace":"","upper_bound":{".class":"Instance","args":[{".class":"TypeVarType","default":{".class":"AnyType","missing_import_name":null,"source_any":null,"type_of_any":4},"fullname":"discord.ui.item.V","id":1,"name":"V","namespace":"discord.ui.item.Item","upper_bound":"discord.ui.view.View","values":[],"variance":1}],"type_ref":"discord.ui.item.Item"},"values":[],"variance":0},"slots":null,"tuple_type":null,"type_vars":["V"],"typeddict_type":null}},"ItemCallbackType":{".class":"SymbolTableNode","kind":"Gdef","module_public":false,"node":{".class":"TypeAlias","alias_tvars":[{".class":"TypeVarType","default":{".class":"AnyType","missing_import_name":null,"source_any":null,"type_of_any":4},"fullname":"discord.ui.item.V","id":1,"name":"V","namespace":"discord.ui.item.ItemCallbackType","upper_bound":"discord.ui.view.View","values":[],"variance":1},{".class":"TypeVarType","default":{".class":"AnyType","missing_import_name":null,"source_any":null,"type_of_any":4},"fullname":"discord.ui.item.I","id":2,"name":"I","namespace":"discord.ui.item.ItemCallbackType","upper_bound":{".class":"Instance","args":[{".class":"AnyType","missing_import_name":null,"source_any":null,"type_of_any":2}],"type_ref":"discord.ui.item.Item"},"values":[],"variance":0}],"column":0,"fullname":"discord.ui.item.ItemCallbackType","line":45,"no_args":false,"normalized":false,"target":{".class":"CallableType","arg_kinds":[0,0,0],"arg_names":[null,null,null],"arg_types":[{".class":"TypeVarType","default":{".class":"AnyType","missing_import_name":null,"source_any":null,"type_of_any":4},"fullname":"discord.ui.item.V","id":1,"name":"V","namespace":"discord.ui.item.ItemCallbackType","upper_bound":"discord.ui.view.View","values":[],"variance":1},{".class":"Instance","args":[{".class":"AnyType","missing_import_name":null,"source_any":null,"type_of_any":6}],"type_ref":"discord.interactions.Interaction"},{".class":"TypeVarType","default":{".class":"AnyType","missing_import_name":null,"source_any":null,"type_of_any":4},"fullname":"discord.ui.item.I","id":2,"name":"I","namespace":"discord.ui.item.ItemCallbackType","upper_bound":{".class":"Instance","args":[{".class":"AnyType","missing_import_name":null,"source_any":null,"type_of_any":2}],"type_ref":"discord.ui.item.Item"},"values":[],"variance":0}],"bound_args":[],"def_extras":{},"fallback":"builtins.function","from_concatenate":false,"implicit":false,"imprecise_arg_kinds":false,"is_ellipsis_args":false,"name":null,"ret_type":{".class":"Instance","args":[{".class":"AnyType","missing_import_name":null,"source_any":null,"type_of_any":6},{".class":"AnyType","missing_import_name":null,"source_any":null,"type_of_any":6},{".class":"AnyType","missing_import_name":null,"source_any":null,"type_of_any":6}],"type_ref":"typing.Coroutine"},"type_guard":null,"unpack_kwargs":false,"variables":[]}}},"Optional":{".class":"SymbolTableNode","cross_ref":"typing.Optional","kind":"Gdef","module_public":false},"TYPE_CHECKING":{".class":"SymbolTableNode","cross_ref":"typing.TYPE_CHECKING","kind":"Gdef","module_public":false},"Tuple":{".class":"SymbolTableNode","cross_ref":"typing.Tuple","kind":"Gdef","module_public":false},"Type":{".class":"SymbolTableNode","cross_ref":"typing.Type","kind":"Gdef","module_public":false},"TypeVar":{".class":"SymbolTableNode","cross_ref":"typing.TypeVar","kind":"Gdef","module_public":false},"V":{".class":"SymbolTableNode","kind":"Gdef","module_public":false,"node":{".class":"TypeVarExpr","default":{".class":"AnyType","missing_import_name":null,"source_any":null,"type_of_any":4},"fullname":"discord.ui.item.V","name":"V","upper_bound":"discord.ui.view.View","values":[],"variance":1}},"View":{".class":"SymbolTableNode","cross_ref":"discord.ui.view.View","kind":"Gdef","module_public":false},"__all__":{".class":"SymbolTableNode","kind":"Gdef","module_public":false,"node":{".class":"Var","flags":["is_inferred","has_explicit_value"],"fullname":"discord.ui.item.__all__","name":"__all__","type":{".class":"TupleType","implicit":false,"items":["builtins.str"],"partial_fallback":{".class":"Instance","args":[{".class":"AnyType","missing_import_name":null,"source_any":null,"type_of_any":6}],"type_ref":"builtins.tuple"}}}},"__annotations__":{".class":"SymbolTableNode","kind":"Gdef","module_public":false,"node":{".class":"Var","flags":["is_ready"],"fullname":"discord.ui.item.__annotations__","name":"__annotations__","type":{".class":"Instance","args":["builtins.str",{".class":"AnyType","missing_import_name":null,"source_any":null,"type_of_any":6}],"type_ref":"builtins.dict"}}},"__doc__":{".class":"SymbolTableNode","kind":"Gdef","module_public":false,"node":{".class":"Var","flags":["is_ready"],"fullname":"discord.ui.item.__doc__","name":"__doc__","type":"builtins.str"}},"__file__":{".class":"SymbolTableNode","kind":"Gdef","module_public":false,"node":{".class":"Var","flags":["is_ready"],"fullname":"discord.ui.item.__file__","name":"__file__","type":"builtins.str"}},"__name__":{".class":"SymbolTableNode","kind":"Gdef","module_public":false,"node":{".class":"Var","flags":["is_ready"],"fullname":"discord.ui.item.__name__","name":"__name__","type":"builtins.str"}},"__package__":{".class":"SymbolTableNode","kind":"Gdef","module_public":false,"node":{".class":"Var","flags":["is_ready"],"fullname":"discord.ui.item.__package__","name":"__package__","type":"builtins.str"}},"annotations":{".class":"SymbolTableNode","cross_ref":"__future__.annotations","kind":"Gdef","module_public":false}},"path":"c:\\Python312\\Lib\\site-packages\\discord\\ui\\item.py"}